{"fundamental":{"code":"512634","name":"Savera Industries Ltd","url":"https://www.screener.in/company/512634/","overview":{"Market Cap":"\u20b9 181 Cr.","Current Price":"\u20b9 152","High / Low":"\u20b9 189 / 133","Stock P/E":"16.3","Book Value":"\u20b9 81.4","Dividend Yield":"1.97 %","ROCE":"15.0 %","ROE":"12.0 %","Face Value":"\u20b9 10.0"},"growth":{"Compounded Sales Growth":{"10 Years":"4%","5 Years":"39%","3 Years":"19%","TTM":"28%"},"Compounded Profit Growth":{"10 Years":"16%","5 Years":"38%","3 Years":"3%","TTM":"-7%"},"Stock Price CAGR":{"10 Years":"9%","5 Years":"26%","3 Years":"27%","1 Year":"1%"},"Return on Equity":{"10 Years":"9%","5 Years":"11%","3 Years":"13%","Last Year":"12%"}},"quarters":{"headers":["Jun 2023","Sep 2023","Dec 2023","Mar 2024","Jun 2024","Sep 2024","Dec 2024","Mar 2025","Jun 2025","Sep 2025","Dec 2025","Mar 2026"],"rows":{"Sales":["17.35","18.34","17.47","18.99","17.93","20.60","19.29","21.83","22.08","25.50","27.17","27.58"],"OPM":["21.21%","22.36%","18.49%","11.48%","14.67%","27.23%","14.00%","17.96%","20.47%","23.10%","16.56%","10.15%"],"Net Profit":["2.69","3.01","2.70","1.90","2.67","4.74","2.02","3.81","5.75","3.60","2.77","0.70"],"EPS":["2.26","2.52","2.26","1.59","2.24","3.97","1.69","3.19","4.82","3.02","2.32","0.59"]}},"profit_loss":{"headers":["Mar 2015","Mar 2016","Mar 2017","Mar 2018","Mar 2019","Mar 2020","Mar 2021","Mar 2022","Mar 2023","Mar 2024","Mar 2025","Mar 2026"],"rows":{"Sales":["62","66","68","72","72","67","20","32","61","72","80","102"],"Expenses":["51","54","56","60","59","56","21","30","47","59","65","85"],"Operating Profit":["12","12","13","12","13","11","-1","2","14","13","15","18"],"OPM %":["18%","18%","18%","17%","18%","16%","-5%","5%","23%","18%","19%","17%"],"Other Income":["1","1","-1","-0","1","0","1","1","4","3","5","6"],"Interest":["3","3","2","1","1","1","0","0","0","0","0","1"],"Depreciation":["5","4","4","4","3","5","4","3","3","3","3","7"],"Profit before tax":["4","6","5","7","9","6","-5","-1","15","13","16","16"],"Tax %":["27%","58%","41%","24%","32%","27%","-10%","14%","19%","23%","18%","22%"],"Net Profit":["3","2","3","5","6","4","-4","-1","12","10","13","13"],"EPS in Rs":["2.42","2.04","2.63","4.30","5.26","3.59","-3.44","-0.67","10.45","8.64","11.10","10.75"],"Dividend Payout %":["50%","74%","57%","58%","23%","33%","0%","0%","29%","35%","27%","28%"]}},"balance_sheet":{"headers":["Mar 2015","Mar 2016","Mar 2017","Mar 2018","Mar 2019","Mar 2020","Mar 2021","Mar 2022","Mar 2023","Mar 2024","Mar 2025","Mar 2026"],"rows":{"Equity Capital":["12","12","12","12","12","12","12","12","12","12","12","12"],"Reserves":["39","39","42","44","47","49","46","46","59","66","76","85"],"Borrowings":["23","18","13","7","3","3","5","2","4","4","6","7"],"Other Liabilities":["12","13","12","12","11","9","6","7","8","14","12","13"],"Total Liabilities":["86","82","79","75","73","73","69","67","83","95","106","118"],"Fixed Assets":["67","66","65","61","59","59","55","52","46","42","45","44"],"CWIP":["0","0","0","0","0","0","0","0","0","0","0","0"],"Investments":["3","0","2","2","2","2","2","3","13","15","18","31"],"Other Assets":["15","15","12","11","11","13","11","11","24","39","43","42"],"Total Assets":["86","82","79","75","73","73","69","67","83","95","106","118"]}},"cash_flow":{"headers":["Mar 2015","Mar 2016","Mar 2017","Mar 2018","Mar 2019","Mar 2020","Mar 2021","Mar 2022","Mar 2023","Mar 2024","Mar 2025","Mar 2026"],"rows":{"Cash from Operating Activity":["13","16","10","11","9","10","-4","4","12","8","13","14"],"Cash from Investing Activity":["-4","-5","-3","-0","-2","-3","1","-2","-13","-1","-10","-3"],"Cash from Financing Activity":["-8","-11","-7","-11","-7","-6","-1","-1","0","-4","-6","-7"],"Net Cash Flow":["1","-0","-0","-0","0","1","-4","2","-0","3","-3","4"],"Free Cash Flow":["12","12","5","10","8","9","-4","4","20","6","13","16"],"CFO/OP":["129%","147%","107%","118%","100%","108%","332%","313%","109%","82%","109%","100%"]}},"ratios":{"headers":["Mar 2015","Mar 2016","Mar 2017","Mar 2018","Mar 2019","Mar 2020","Mar 2021","Mar 2022","Mar 2023","Mar 2024","Mar 2025","Mar 2026"],"rows":{"Debtor Days":["7","11","14","11","7","6","12","8","7","8","8","9"],"Inventory Days":["5","7","","","6","8","26","13","12","6","8","11"],"Days Payable":["59","44","","","40","38","110","54","34","68","62","43"],"Cash Conversion Cycle":["-47","-27","14","11","-26","-24","-72","-34","-15","-54","-46","-22"],"Working Capital Days":["-82","-68","-58","-41","-27","-25","-104","-59","-38","-44","-52","-41"],"ROCE %":["10%","12%","13%","14%","16%","11%","-6%","-0%","19%","17%","17%","15%"]}},"shareholding":{"headers":["Jun 2023","Sep 2023","Dec 2023","Mar 2024","Jun 2024","Sep 2024","Dec 2024","Mar 2025","Jun 2025","Sep 2025","Dec 2025","Mar 2026"],"rows":{"Promoters":["62.80%","62.80%","62.80%","62.80%","62.81%","62.81%","62.81%","62.81%","62.81%","62.81%","62.81%","64.62%"],"DIIs":["0.00%","0.00%","0.00%","0.88%","0.52%","0.00%","0.00%","0.00%","0.00%","0.00%","0.00%","0.00%"],"Public":["37.19%","37.20%","37.20%","36.31%","36.66%","37.20%","37.19%","37.21%","37.20%","37.20%","37.21%","35.38%"],"No. of Shareholders":["5,005","5,015","5,482","6,679","6,675","6,059","6,136","5,956","5,836","5,847","5,674","5,443"]}},"insights":{"yearly":{"periods":["Mar 2014","Mar 2015","Mar 2016","Mar 2017","Mar 2018","Mar 2019","Mar 2020","Mar 2021","Mar 2022","Mar 2023","Mar 2024","Mar 2025"],"rows":[{"metric":"Room Occupancy","unit":"%","values":{"Mar 2025":"xx.xxxx.xxxx.xxxx.xxxx.xxxx.xxxx.xxxx.xxxx.xxxx.xxxx.xxxx.xxxxx,xxxxxx,xxxxxx,xxxxxx,xxxxxxxxxxxxxxxx.xxx.xxxxUnlock insightsFree users can unlock up to 5 insights tables per month.Unlock"}}]}},"pros":["Company is almost debt free.","Company is expected to give good quarter","Company has been maintaining a healthy dividend payout of 29.9%","Promoter holding has increased by 1.82% over last quarter."],"cons":["Company has a low return on equity of 13.1% over last 3 years.","Earnings include an other income of Rs.6.15 Cr."],"analysis":{"trends":{"yearly":{"Sales":{"label":"Increasing","n":6,"unit":"yrs"},"Net Profit":{"label":"Inconsistent","n":1,"unit":"yrs"},"OPM%":{"label":"Inconsistent","n":2,"unit":"yrs"},"EPS":{"label":"Inconsistent","n":2,"unit":"yrs"},"Reserves":{"label":"Increasing","n":5,"unit":"yrs"},"Net Cash Flow":{"label":"Inconsistent","n":2,"unit":"yrs"},"Operating Cash Flow":{"label":"Inconsistent","n":3,"unit":"yrs"},"ROCE":{"label":"Inconsistent","n":2,"unit":"yrs"}},"quarterly":{"Sales":{"label":"Increasing","n":6,"unit":"qtrs"},"Net Profit":{"label":"Decreasing","n":4,"unit":"qtrs"},"OPM%":{"label":"Inconsistent","n":3,"unit":"qtrs"},"EPS":{"label":"Decreasing","n":4,"unit":"qtrs"},"Promoter Holding":{"label":"Inconsistent","n":2,"unit":"qtrs"}}},"cyclical":{"label":"CYCLICAL","positive_quarters":["Jun","Sep"],"negative_quarters":["Mar","Dec"]},"growth_insight":{"label":"FUNDAMENTALS-LED","long":"Profit grew 38% vs price 26% (5Y) \u2014 fundamentals outpacing the stock; potentially undervalued.","recent":"Recently, price growth exceeds profit growth by 8% \u2014 expectations running ahead of delivery."},"money_flow":{"label":"NEUTRAL","change":null,"note":"Insufficient shareholding history."},"dcf":{"ok":true,"inputs":{"earnings":13,"growth":18.0,"discount":10,"terminal_growth":2,"years":10,"terminal_multiple":12.8},"dcf":{"rows":[{"year":1,"earnings":15,"growth":18.0,"pv":14},{"year":2,"earnings":18,"growth":18.0,"pv":15},{"year":3,"earnings":21,"growth":18.0,"pv":16},{"year":4,"earnings":25,"growth":18.0,"pv":17},{"year":5,"earnings":30,"growth":18.0,"pv":18},{"year":6,"earnings":35,"growth":18.0,"pv":20},{"year":7,"earnings":41,"growth":18.0,"pv":21},{"year":8,"earnings":49,"growth":18.0,"pv":23},{"year":9,"earnings":58,"growth":18.0,"pv":24},{"year":10,"earnings":68,"growth":18.0,"pv":26}],"pv_1_n":195,"terminal_year_cf":69,"terminal_value":868,"pv_terminal":334,"effective_multiple":12.8,"total_pv":530},"reverse":{"rows":[{"year":1,"earnings":13,"growth":3.19,"pv":12},{"year":2,"earnings":14,"growth":3.19,"pv":11},{"year":3,"earnings":14,"growth":3.19,"pv":11},{"year":4,"earnings":15,"growth":3.19,"pv":10},{"year":5,"earnings":15,"growth":3.19,"pv":9},{"year":6,"earnings":16,"growth":3.19,"pv":9},{"year":7,"earnings":16,"growth":3.19,"pv":8},{"year":8,"earnings":17,"growth":3.19,"pv":8},{"year":9,"earnings":17,"growth":3.19,"pv":7},{"year":10,"earnings":18,"growth":3.19,"pv":7}],"pv_1_n":93,"terminal_year_cf":18,"terminal_value":227,"pv_terminal":87,"effective_multiple":12.8,"total_pv":181,"implied_growth":3.19},"intrinsic_total":530,"intrinsic_per_share":445,"current_price":152.0,"market_cap":181.0,"margin_of_safety":65.8}}},"prices":{"ok":true,"ticker":"512634.BO","yearwise":[{"year":2002,"ret":-21.11},{"year":2003,"ret":95.77},{"year":2004,"ret":76.62},{"year":2005,"ret":72.43},{"year":2006,"ret":82.57},{"year":2007,"ret":53.41},{"year":2008,"ret":-72.68},{"year":2009,"ret":41.53},{"year":2010,"ret":117.78},{"year":2011,"ret":-24.96},{"year":2012,"ret":53.76},{"year":2013,"ret":-31.01},{"year":2014,"ret":35.17},{"year":2015,"ret":54.76},{"year":2016,"ret":0.19},{"year":2017,"ret":42.67},{"year":2018,"ret":-9.55},{"year":2019,"ret":-34.0},{"year":2020,"ret":-13.75},{"year":2021,"ret":14.78},{"year":2022,"ret":59.01},{"year":2023,"ret":71.71},{"year":2024,"ret":44.83},{"year":2025,"ret":-12.91},{"year":2026,"ret":6.44}],"heatmap":{"months":["Jan","Feb","Mar","Apr","May","Jun","Jul","Aug","Sep","Oct","Nov","Dec"],"rows":[{"year":2002,"vals":[null,null,null,null,null,null,null,-18.87,-16.28,0.69,-6.9,5.19],"annual":-33.02},{"year":2003,"vals":[-8.45,30.77,-17.65,15.71,-16.67,9.93,-5.66,15.71,-20.74,9.03,40.29,41.55],"annual":95.76},{"year":2004,"vals":[-20.86,-6.36,1.94,4.0,-17.49,13.76,14.73,24.83,12.4,9.7,-0.28,36.01],"annual":76.63},{"year":2005,"vals":[-10.39,2.27,1.11,8.79,26.26,33.28,17.29,-1.84,-6.29,-25.91,47.09,-13.56],"annual":72.41},{"year":2006,"vals":[38.0,-16.61,11.22,28.18,-9.71,-12.05,-7.69,9.73,24.15,0.45,13.64,-2.39],"annual":82.54},{"year":2007,"vals":[-1.49,-6.28,-8.76,28.55,-12.11,3.85,-5.5,3.85,3.41,9.82,17.82,18.19],"annual":53.39},{"year":2008,"vals":[-8.93,-11.95,-9.14,1.25,-13.58,-19.43,0.18,0.0,-8.45,-31.0,-24.64,11.54],"annual":-72.68},{"year":2009,"vals":[3.28,-20.2,-9.21,13.59,53.35,-7.94,3.16,-15.04,23.99,-3.39,5.61,6.37],"annual":41.52},{"year":2010,"vals":[12.98,10.06,-1.61,32.76,-18.52,-3.11,12.85,35.81,16.37,14.97,-9.55,-8.42],"annual":117.79},{"year":2011,"vals":[-11.41,6.7,-3.82,-0.13,-3.46,3.45,6.42,-7.72,-0.24,0.0,-5.68,-10.46],"annual":-24.97},{"year":2012,"vals":[-0.8,12.1,8.06,-2.13,8.44,-6.27,4.02,-14.93,19.59,4.44,2.63,13.41],"annual":53.77},{"year":2013,"vals":[6.77,-12.79,-7.85,6.52,2.35,-16.21,-3.98,6.14,4.98,-30.99,30.52,-8.68],"annual":-31.02},{"year":2014,"vals":[9.18,4.57,-2.26,-4.18,9.34,26.31,-14.94,13.85,-7.56,8.15,12.17,-15.7],"annual":35.19},{"year":2015,"vals":[1.23,-0.73,-6.59,1.83,2.56,-2.75,0.26,15.38,1.53,32.58,14.07,-8.62],"annual":54.75},{"year":2016,"vals":[19.51,-33.33,11.45,3.18,15.94,2.03,9.42,-13.72,-2.17,8.33,4.62,-11.69],"annual":0.19},{"year":2017,"vals":[3.33,-5.0,-1.36,16.94,-5.29,6.29,3.21,-4.32,0.08,5.96,15.74,3.26],"annual":42.66},{"year":2018,"vals":[5.66,-11.07,-1.42,0.79,-9.29,-4.8,-3.68,20.92,-11.64,0.38,10.63,-1.84],"annual":-9.56},{"year":2019,"vals":[0.9,-10.81,5.57,-3.42,-7.69,-16.0,-8.73,-1.32,0.0,-3.11,4.89,1.35],"annual":-34.0},{"year":2020,"vals":[-0.22,-5.44,-22.91,4.57,-11.66,10.56,-4.03,9.8,-3.68,0.74,0.73,12.75],"annual":-13.73},{"year":2021,"vals":[3.98,6.06,1.17,2.42,1.24,8.11,3.8,-12.48,7.01,5.29,-4.62,-6.0],"annual":14.78},{"year":2022,"vals":[9.74,0.82,7.49,12.15,-19.98,-3.46,17.61,31.24,-4.08,1.32,8.84,-5.46],"annual":59.04},{"year":2023,"vals":[-0.49,-13.16,-10.35,12.6,13.82,14.63,11.2,-5.22,-0.14,25.67,11.64,2.17],"annual":71.7},{"year":2024,"vals":[29.18,-11.95,-12.49,16.79,-14.12,8.9,20.15,4.43,6.68,-15.22,9.27,7.43],"annual":44.83},{"year":2025,"vals":[-4.22,-22.87,4.13,1.17,12.11,4.84,-3.11,7.83,-4.63,3.41,-5.17,-2.56],"annual":-12.91},{"year":2026,"vals":[2.07,4.36,8.35,-2.64,-7.07,1.94,null,null,null,null,null,null],"annual":6.45}]},"risk":{"avg_weekly":0.65,"weekly_std":8.22,"ann_vol":59.27,"max_drawdown":-85.37,"pct_positive":49.64,"sharpe":0.57,"sortino":0.95},"technical":{"ret_3m":-3.77,"excess_3m":-6.23,"ret_6m":2.46,"excess_6m":7.17,"ret_12m":1.78,"excess_12m":2.27,"rs_rating":49,"price":152.05,"above_50dma":false,"above_200dma":false,"golden_cross":true,"pos_52w":38.51,"dist_52w_high":-13.61,"benchmark":"Nifty 500"}},"signal":{"label":"NEUTRAL","composite":56,"confidence":"Medium","blocks":{"results":{"score":47,"reasons":["Sales +26% YoY","strong sales growth","sales up QoQ","Net profit -82% YoY","earnings growth decelerating"],"metrics":{"sales_yoy":26.3,"np_yoy":-81.6,"np_qoq":-74.7,"eps_yoy":-81.5,"accel":-118.8,"opm_exp":-7.8}},"technical":{"score":47,"reasons":["below 200-DMA","golden cross (50>200)"],"metrics":{"rs_rating":49,"excess_3m":-6.23,"excess_12m":2.27,"above_200dma":false,"golden_cross":true,"pos_52w":38.51}},"fundamental":{"score":73,"reasons":["multi-year sales uptrend","ROCE 15%","DCF margin of safety 66%"],"metrics":{"roe":12.0,"roce":15.0,"dcf_mos":65.8}}},"weights":{"results":0.3,"technical":0.35,"fundamental":0.35},"reasons_pos":["Sales +26% YoY","strong sales growth","sales up QoQ","multi-year sales uptrend","ROCE 15%","DCF margin of safety 66%"],"reasons_neg":["Net profit -82% YoY","earnings growth decelerating","below 200-DMA"],"ticker":"512634.BO","disclaimer":"Rules-based screen for research/education only \u2014 not personalized investment advice. Verify independently before any decision.","bias_check":{"risk":"LOW","principle":"Markets price expectations, not your conviction \u2014 weigh valuation, the macro and the data, not just the story.","flags":[{"level":"ok","title":"No major bias red-flags","note":"Valuation, momentum and the macro are broadly consistent with the verdict. Still do your own diligence.","lesson":"Being aware of your biases \u2014 not proximity \u2014 is the edge."}],"source":"Insider-Bias checklist"}}}