{"fundamental":{"code":"513460","name":"Mahalaxmi Seamless Ltd","url":"https://www.screener.in/company/513460/","overview":{"Market Cap":"\u20b9 4.16 Cr.","Current Price":"\u20b9 7.88","High / Low":"\u20b9 10.6 / 7.05","Stock P/E":"","Book Value":"\u20b9 -1.02","Dividend Yield":"0.00 %","ROCE":"15.1 %","ROE":"%","Face Value":"\u20b9 10.0"},"growth":{"Compounded Sales Growth":{"10 Years":"-16%","5 Years":"0%","3 Years":"1%","TTM":"2%"},"Compounded Profit Growth":{"10 Years":"7%","5 Years":"%","3 Years":"%","TTM":"-128%"},"Stock Price CAGR":{"10 Years":"10%","5 Years":"16%","3 Years":"-2%","1 Year":"-26%"},"Return on Equity":{"10 Years":"%","5 Years":"%","3 Years":"%","Last Year":"%"}},"quarters":{"headers":["Jun 2023","Sep 2023","Dec 2023","Mar 2024","Jun 2024","Sep 2024","Dec 2024","Mar 2025","Jun 2025","Sep 2025","Dec 2025","Mar 2026"],"rows":{"Sales":["0.45","0.47","0.46","0.47","0.45","0.49","0.47","0.45","0.45","0.45","0.48","0.51"],"OPM":["46.67%","40.43%","36.96%","36.17%","42.22%","36.73%","38.30%","40.00%","48.89%","40.00%","31.25%","-50.98%"],"Net Profit":["0.05","-1.54","0.03","0.21","0.08","0.06","0.04","0.07","0.09","0.10","0.06","-0.33"],"EPS":["0.09","-2.92","0.06","0.40","0.15","0.11","0.08","0.13","0.17","0.19","0.11","-0.62"]}},"profit_loss":{"headers":["Mar 2015","Mar 2016","Mar 2017","Mar 2018","Mar 2019","Mar 2020","Mar 2021","Mar 2022","Mar 2023","Mar 2024","Mar 2025","Mar 2026"],"rows":{"Sales":["18.62","11.04","10.72","3.90","1.87","1.87","1.91","2.02","1.83","1.84","1.86","1.89"],"Expenses":["18.07","11.08","12.34","3.59","1.21","1.25","0.97","0.99","1.00","1.09","1.13","1.60"],"Operating Profit":["0.55","-0.04","-1.62","0.31","0.66","0.62","0.94","1.03","0.83","0.75","0.73","0.29"],"OPM %":["2.95%","-0.36%","-15.11%","7.95%","35.29%","33.16%","49.21%","50.99%","45.36%","40.76%","39.25%","15.34%"],"Other Income":["0.93","0.15","0.63","-0.20","0.11","0.28","0.33","0.13","0.09","-1.53","0.03","0.02"],"Interest":["0.90","0.93","0.62","0.51","0.30","0.43","0.46","0.19","0.11","0.10","0.21","0.21"],"Depreciation":["0.65","0.59","0.60","0.60","0.60","0.58","0.55","0.52","0.47","0.44","0.36","0.20"],"Profit before tax":["-0.07","-1.41","-2.21","-1.00","-0.13","-0.11","0.26","0.45","0.34","-1.32","0.19","-0.10"],"Tax %":["85.71%","3.55%","2.71%","0.00%","-30.77%","-9.09%","-53.85%","-20.00%","-14.71%","-6.82%","-31.58%","-20.00%"],"Net Profit":["-0.13","-1.46","-2.28","-1.00","-0.09","-0.09","0.40","0.54","0.39","-1.24","0.25","-0.07"],"EPS in Rs":["-0.25","-2.76","-4.32","-1.89","-0.17","-0.17","0.76","1.02","0.74","-2.35","0.47","-0.13"],"Dividend Payout %":["0.00%","0.00%","0.00%","0.00%","0.00%","0.00%","0.00%","0.00%","0.00%","0.00%","0.00%","0.00%"]}},"balance_sheet":{"headers":["Mar 2015","Mar 2016","Mar 2017","Mar 2018","Mar 2019","Mar 2020","Mar 2021","Mar 2022","Mar 2023","Mar 2024","Mar 2025","Mar 2026"],"rows":{"Equity Capital":["5.29","5.29","5.29","5.29","5.29","5.28","5.28","5.28","5.28","5.28","5.28","5.28"],"Reserves":["-1.18","-2.65","-4.92","-5.92","-6.01","-6.09","-5.69","-5.15","-4.76","-6.01","-5.75","-5.82"],"Borrowings":["4.71","8.04","4.76","4.19","6.32","5.47","4.90","1.84","1.36","1.54","1.41","1.06"],"Other Liabilities":["7.89","5.08","4.66","3.34","3.03","2.90","2.72","2.35","2.22","2.34","2.04","2.49"],"Total Liabilities":["16.71","15.76","9.79","6.90","8.63","7.56","7.21","4.32","4.10","3.15","2.98","3.01"],"Fixed Assets":["6.82","6.35","5.88","5.40","4.80","4.23","3.69","3.18","2.85","2.42","2.21","2.02"],"CWIP":["0.00","0.00","0.00","0.00","0.00","0.00","0.00","0.00","0.00","0.00","0.00","0.00"],"Investments":["0.00","0.00","0.00","0.00","0.00","0.00","0.00","0.00","0.00","0.00","0.00","0.03"],"Other Assets":["9.89","9.41","3.91","1.50","3.83","3.33","3.52","1.14","1.25","0.73","0.77","0.96"],"Total Assets":["16.71","15.76","9.79","6.90","8.63","7.56","7.21","4.32","4.10","3.15","2.98","3.01"]}},"cash_flow":{"headers":["Mar 2015","Mar 2016","Mar 2017","Mar 2018","Mar 2019","Mar 2020","Mar 2021","Mar 2022","Mar 2023","Mar 2024","Mar 2025","Mar 2026"],"rows":{"Cash from Operating Activity":["1.69","-2.72","1.11","1.30","0.58","0.50","0.69","-5.00","0.82","-0.61","0.37","0.27"],"Cash from Investing Activity":["0.59","-0.32","0.93","-0.07","-2.36","0.85","0.25","8.07","0.06","0.53","-0.31","-0.20"],"Cash from Financing Activity":["-2.01","2.60","-2.05","-1.48","1.71","-1.27","-0.93","-2.98","-0.47","0.07","-0.34","-0.56"],"Net Cash Flow":["0.27","-0.43","-0.01","-0.25","-0.07","0.08","0.01","0.10","0.40","-0.01","-0.28","-0.49"],"Free Cash Flow":["1.69","-2.83","1.16","1.17","0.58","0.49","0.68","-5.01","0.67","-0.62","0.17","0.26"],"CFO/OP":["307%","6,625%","-75%","435%","106%","87%","83%","58%","99%","-81%","51%","93%"]}},"ratios":{"headers":["Mar 2015","Mar 2016","Mar 2017","Mar 2018","Mar 2019","Mar 2020","Mar 2021","Mar 2022","Mar 2023","Mar 2024","Mar 2025","Mar 2026"],"rows":{"Debtor Days":["57.83","31.08","10.21","16.85","31.23","33.18","42.04","34.33","9.97","7.93","31.40","30.90"],"Inventory Days":["151.30","473.89","154.54","12.71","","","","","","","",""],"Days Payable":["200.62","226.97","133.20","147.09","","","","","","","",""],"Cash Conversion Cycle":["8.51","277.99","31.56","-117.53","31.23","33.18","42.04","34.33","9.97","7.93","31.40","30.90"],"Working Capital Days":["-43.91","-93.23","-131.43","-143.19","-286.93","-191.28","-170.08","-65.05","-195.46","-388.80","-347.34","-289.68"],"ROCE %":["8.87%","-4.51%","-22.52%","-5.29%","3.71%","6.24%","15.74%","19.81%","23.38%","26.02%","45.71%","15.07%"]}},"shareholding":{"headers":["Jun 2023","Sep 2023","Dec 2023","Mar 2024","Jun 2024","Sep 2024","Dec 2024","Mar 2025","Jun 2025","Sep 2025","Dec 2025","Mar 2026"],"rows":{"Promoters":["45.52%","45.52%","45.52%","45.84%","45.84%","45.84%","45.84%","45.84%","45.84%","45.84%","45.84%","45.84%"],"Public":["54.48%","54.48%","54.48%","54.16%","54.16%","54.16%","54.16%","54.16%","54.16%","54.15%","54.16%","54.16%"],"No. of Shareholders":["5,258","5,252","5,326","5,301","5,347","5,416","5,586","5,581","5,554","5,646","5,661","5,636"]}},"insights":{"yearly":{"periods":["Mar 2015","Mar 2016","Mar 2017","Mar 2018","Mar 2019","Mar 2020","Mar 2021","Mar 2022","Mar 2023","Mar 2024","Mar 2025"],"rows":[{"metric":"Factory Status","unit":"Operational Status","values":{"Mar 2025":"xxxxxxxxxxxx.xxx.xxxxx.xxxxx.xxxxx.xxxxx.xxxxx.xxxxx.xxxxx.xxxxx.xxx.xxx.xxx.xxx.xxx.xxx.xxx.xxx.xxx.xxx.xxxxxxxxxxxx.xxx.xxx.xxx.xxx.xxx.xxx.xxx.xxUnlock insightsFree users can unlock up to 5 insights tables per month.Unlock"}}]}},"pros":["Company has reduced debt."],"cons":["Company has low interest coverage ratio.","The company has delivered a poor sales growth of -0.21% over past five years.","Company's cost of borrowing seems high"],"analysis":{"trends":{"yearly":{"Sales":{"label":"Increasing","n":4,"unit":"yrs"},"Net Profit":{"label":"Inconsistent","n":2,"unit":"yrs"},"OPM%":{"label":"Decreasing","n":5,"unit":"yrs"},"EPS":{"label":"Inconsistent","n":2,"unit":"yrs"},"Reserves":{"label":"Inconsistent","n":2,"unit":"yrs"},"Net Cash Flow":{"label":"Decreasing","n":4,"unit":"yrs"},"Operating Cash Flow":{"label":"Inconsistent","n":2,"unit":"yrs"},"ROCE":{"label":"Inconsistent","n":2,"unit":"yrs"}},"quarterly":{"Sales":{"label":"Inconsistent","n":3,"unit":"qtrs"},"Net Profit":{"label":"Inconsistent","n":3,"unit":"qtrs"},"OPM%":{"label":"Decreasing","n":4,"unit":"qtrs"},"EPS":{"label":"Inconsistent","n":3,"unit":"qtrs"},"Promoter Holding":{"label":"Inconsistent","n":1,"unit":"qtrs"}}},"cyclical":{"label":"CYCLICAL","positive_quarters":["Mar"],"negative_quarters":["Jun","Sep","Dec"]},"growth_insight":{"label":"PRICE-LED","long":"Insufficient data.","recent":"Recently, price growth exceeds profit growth by 102% \u2014 expectations running ahead of delivery."},"money_flow":{"label":"NEUTRAL","change":null,"note":"Insufficient shareholding history."},"dcf":{"ok":false,"reason":"no positive earnings"}}},"prices":{"ok":true,"ticker":"513460.BO","yearwise":[{"year":2002,"ret":438.89},{"year":2003,"ret":-26.8},{"year":2004,"ret":133.1},{"year":2005,"ret":180.97},{"year":2006,"ret":-39.67},{"year":2007,"ret":153.32},{"year":2008,"ret":-80.03},{"year":2009,"ret":28.73},{"year":2010,"ret":4.35},{"year":2011,"ret":-48.78},{"year":2012,"ret":-43.28},{"year":2013,"ret":-12.05},{"year":2014,"ret":73.91},{"year":2015,"ret":-21.25},{"year":2016,"ret":-17.3},{"year":2017,"ret":66.79},{"year":2018,"ret":8.29},{"year":2019,"ret":-22.95},{"year":2020,"ret":-25.38},{"year":2021,"ret":140.67},{"year":2022,"ret":-33.56},{"year":2023,"ret":20.81},{"year":2024,"ret":30.53},{"year":2025,"ret":-37.17},{"year":2026,"ret":-8.05}],"heatmap":{"months":["Jan","Feb","Mar","Apr","May","Jun","Jul","Aug","Sep","Oct","Nov","Dec"],"rows":[{"year":2002,"vals":[null,null,null,null,null,null,null,0.0,0.0,5.56,0.0,410.53],"annual":438.92},{"year":2003,"vals":[-31.96,0.0,0.0,-19.7,0.0,52.08,-0.74,6.25,-32.94,8.77,-25.48,53.68],"annual":-26.8},{"year":2004,"vals":[-25.63,-6.44,7.29,18.87,-20.63,23.4,13.45,57.14,62.36,0.78,-10.0,2.16],"annual":133.11},{"year":2005,"vals":[2.11,15.98,-8.16,37.5,26.26,5.28,8.81,33.38,0.52,-28.65,15.33,17.72],"annual":180.93},{"year":2006,"vals":[-5.16,-22.22,-13.12,7.89,-4.04,-30.96,-6.1,4.25,7.45,4.67,24.33,-3.77],"annual":-39.66},{"year":2007,"vals":[8.21,-12.07,-9.41,19.05,14.91,-0.32,9.68,24.6,-1.28,-17.76,27.38,52.5],"annual":153.33},{"year":2008,"vals":[-50.37,-9.31,-15.89,6.3,-3.52,-15.55,5.0,-4.76,-18.18,-15.56,-20.72,11.2],"annual":-80.03},{"year":2009,"vals":[-19.78,0.0,-6.98,53.0,14.71,-10.54,7.96,0.59,10.26,-13.03,-5.2,11.29],"annual":28.72},{"year":2010,"vals":[7.54,-12.13,12.58,27.25,-4.07,-12.05,-6.6,-2.17,63.89,-30.85,-16.67,5.88],"annual":4.35},{"year":2011,"vals":[-13.06,-10.54,-8.07,14.22,-15.03,-11.93,18.09,-25.25,2.78,7.72,-19.91,7.08],"annual":-48.78},{"year":2012,"vals":[3.36,16.79,-19.23,11.23,-11.6,-7.92,-0.98,-19.23,-1.54,-1.56,-16.48,-0.76],"annual":-43.28},{"year":2013,"vals":[3.63,7.38,-9.62,9.51,-1.04,-4.21,-2.38,9.76,-18.29,-3.77,-4.78,5.02],"annual":-12.04},{"year":2014,"vals":[-5.87,-12.01,35.7,-14.51,-10.41,11.36,2.27,-9.53,17.4,36.53,37.46,-11.01],"annual":73.9},{"year":2015,"vals":[-6.25,-0.53,-39.41,0.88,0.88,9.57,0.79,42.52,-4.97,-14.83,9.22,-1.56],"annual":-21.24},{"year":2016,"vals":[-30.0,-18.82,9.22,7.16,-12.89,-9.59,-13.64,45.96,35.34,19.89,14.07,-32.34],"annual":-17.32},{"year":2017,"vals":[21.88,-2.68,-20.23,1.22,0.0,0.2,0.0,5.0,5.9,15.11,35.78,0.0],"annual":66.78},{"year":2018,"vals":[0.0,4.95,0.0,0.0,0.0,0.0,-4.93,3.69,0.0,0.0,0.0,4.67],"annual":8.29},{"year":2019,"vals":[-4.99,-4.92,-4.94,0.0,0.0,-4.95,0.0,4.04,0.0,0.0,-9.64,0.42],"annual":-22.94},{"year":2020,"vals":[-0.69,0.0,0.0,-5.56,0.0,2.94,4.57,-9.56,0.0,-4.98,-4.93,-9.53],"annual":-25.38},{"year":2021,"vals":[-27.91,12.56,-20.27,-7.14,10.77,-7.22,152.99,-34.44,49.64,-7.72,-6.93,82.87],"annual":140.68},{"year":2022,"vals":[-7.83,-23.92,6.24,2.06,-7.58,-7.32,6.13,-14.89,4.7,11.6,4.02,-7.09],"annual":-33.57},{"year":2023,"vals":[-9.71,-5.89,4.76,-18.18,-7.14,27.35,-8.72,13.24,-11.04,22.63,23.93,0.38],"annual":20.82},{"year":2024,"vals":[21.53,-7.09,-11.02,2.57,-4.36,3.3,18.42,-6.59,-9.18,4.49,16.83,4.52],"annual":30.5},{"year":2025,"vals":[4.11,6.27,-34.53,-8.91,10.33,-8.16,-11.18,-3.7,9.87,-3.15,-7.11,11.15],"annual":-37.17},{"year":2026,"vals":[9.92,-8.17,-10.29,17.91,-17.92,4.93,null,null,null,null,null,null],"annual":-8.04}]},"risk":{"avg_weekly":0.56,"weekly_std":10.05,"ann_vol":72.47,"max_drawdown":-96.18,"pct_positive":35.39,"sharpe":0.4,"sortino":0.81},"technical":{"ret_3m":-6.41,"excess_3m":-8.88,"ret_6m":-7.84,"excess_6m":-3.13,"ret_12m":-31.48,"excess_12m":-30.99,"rs_rating":21,"price":7.88,"above_50dma":false,"above_200dma":false,"golden_cross":false,"pos_52w":18.57,"dist_52w_high":-30.27,"benchmark":"Nifty 500"}},"signal":{"label":"SELL","composite":38,"confidence":"Low","blocks":{"results":{"score":41,"reasons":["Sales +13% YoY","sales up QoQ","Net profit -571% YoY","earnings growth decelerating"],"metrics":{"sales_yoy":13.3,"np_yoy":-571.4,"np_qoq":-650.0,"eps_yoy":-576.9,"accel":-621.4,"opm_exp":-91.0}},"technical":{"score":13,"reasons":["RS rating 21 (lagging market)","below 200-DMA"],"metrics":{"rs_rating":21,"excess_3m":-8.88,"excess_12m":-30.99,"above_200dma":false,"golden_cross":false,"pos_52w":18.57}},"fundamental":{"score":61,"reasons":["multi-year sales uptrend","ROCE 15%"],"metrics":{"roe":null,"roce":15.1,"dcf_mos":null}}},"weights":{"results":0.3,"technical":0.35,"fundamental":0.35},"reasons_pos":["Sales +13% YoY","sales up QoQ","multi-year sales uptrend","ROCE 15%"],"reasons_neg":["Net profit -571% YoY","earnings growth decelerating","RS rating 21 (lagging market)","below 200-DMA"],"ticker":"513460.BO","disclaimer":"Rules-based screen for research/education only \u2014 not personalized investment advice. Verify independently before any decision.","bias_check":{"risk":"LOW","principle":"Markets price expectations, not your conviction \u2014 weigh valuation, the macro and the data, not just the story.","flags":[{"level":"ok","title":"Sector tailwind","note":"Capital Goods is in a TAILWIND (tailwind score +0.64) \u2014 the macro backdrop supports the setup.","lesson":"Focus on cycles and change, not insider chatter (the author's actual edge)."}],"source":"Insider-Bias checklist"}}}