{"fundamental":{"code":"541445","name":"Waa Solar Ltd","url":"https://www.screener.in/company/541445/","overview":{"Market Cap":"\u20b9 66.3 Cr.","Current Price":"\u20b9 50.0","High / Low":"\u20b9 84.7 / 40.9","Stock P/E":"","Book Value":"\u20b9 138","Dividend Yield":"0.00 %","ROCE":"3.49 %","ROE":"-0.25 %","Face Value":"\u20b9 10.0"},"growth":{"Compounded Sales Growth":{"10 Years":"-5%","5 Years":"2%","3 Years":"2%","TTM":"-2%"},"Compounded Profit Growth":{"10 Years":"%","5 Years":"%","3 Years":"%","TTM":"-138%"},"Stock Price CAGR":{"10 Years":"%","5 Years":"4%","3 Years":"1%","1 Year":"-35%"},"Return on Equity":{"10 Years":"2%","5 Years":"2%","3 Years":"1%","Last Year":"0%"}},"quarters":{"headers":["Sep 2020","Mar 2021","Sep 2021","Mar 2022","Sep 2022","Mar 2023","Sep 2023","Mar 2024","Sep 2024","Mar 2025","Sep 2025","Mar 2026"],"rows":{"Sales":["11.99","12.44","11.09","12.43","13.38","12.43","12.02","14.05","14.11","13.54","8.53","18.64"],"OPM":["89.49%","86.58%","85.93%","86.73%","79.60%","83.43%","83.78%","54.52%","31.96%","20.68%","72.45%","47.75%"],"Net Profit":["1.75","1.56","1.87","3.08","3.32","3.17","3.34","1.06","-1.43","2.65","0.08","-0.54"],"EPS":["1.32","1.17","1.41","2.32","2.50","2.39","2.52","0.80","-1.08","2.00","0.06","-0.41"]}},"profit_loss":{"headers":["Mar 2015","Mar 2016","Mar 2017","Mar 2018","Mar 2019","Mar 2020","Mar 2021","Mar 2022","Mar 2023","Mar 2024","Mar 2025","Mar 2026"],"rows":{"Sales":["53.66","46.02","25.63","24.37","25.07","24.69","24.16","23.27","25.54","25.79","27.65","27.17"],"Expenses":["19.75","19.33","1.52","3.25","2.28","5.87","2.66","2.96","4.52","7.94","20.34","12.09"],"Operating Profit":["33.91","26.69","24.11","21.12","22.79","18.82","21.50","20.31","21.02","17.85","7.31","15.08"],"OPM %":["63.19%","58.00%","94.07%","86.66%","90.91%","76.23%","88.99%","87.28%","82.30%","69.21%","26.44%","55.50%"],"Other Income":["0.60","0.88","0.44","2.31","3.65","11.24","1.00","0.53","0.38","0.55","2.60","2.71"],"Interest":["13.44","11.79","10.84","10.58","9.50","8.58","7.89","5.69","4.72","3.92","4.93","11.00"],"Depreciation":["9.43","9.44","13.56","9.44","9.44","9.01","9.01","8.95","8.78","8.79","3.74","6.69"],"Profit before tax":["11.64","6.34","0.15","3.41","7.50","12.47","5.60","6.20","7.90","5.69","1.24","0.10"],"Tax %":["0.95%","0.00%","0.00%","19.35%","29.47%","17.48%","40.89%","20.32%","17.85%","22.50%","2.42%","570.00%"],"Net Profit":["11.53","6.34","0.15","2.75","5.29","10.29","3.31","4.94","6.49","4.40","1.22","-0.46"],"EPS in Rs":["288.25","126.80","3.00","2.81","3.98","7.74","2.49","3.72","4.89","3.32","0.92","-0.35"],"Dividend Payout %":["0.00%","0.00%","0.00%","0.00%","0.00%","0.00%","0.00%","0.00%","0.00%","0.00%","0.00%","0.00%"]}},"balance_sheet":{"headers":["Mar 2015","Mar 2016","Mar 2017","Mar 2018","Mar 2019","Mar 2020","Mar 2021","Mar 2022","Mar 2023","Mar 2024","Mar 2025","Mar 2026"],"rows":{"Equity Capital":["0.19","0.27","0.27","4.88","6.63","6.63","6.63","13.27","13.27","13.27","13.27","13.27"],"Reserves":["81.45","109.32","71.12","111.63","142.97","156.56","159.87","158.18","164.67","169.07","170.29","169.83"],"Borrowings":["122.20","88.27","86.00","95.65","83.01","73.31","62.27","51.01","39.34","37.58","116.64","152.73"],"Other Liabilities":["14.98","0.21","0.33","2.99","38.48","5.99","3.84","3.22","3.29","2.71","5.06","50.33"],"Total Liabilities":["218.82","198.07","157.72","215.15","271.09","242.49","232.61","225.68","220.57","222.63","305.26","386.16"],"Fixed Assets":["126.80","117.36","65.45","98.49","89.08","76.44","67.43","58.47","50.15","40.59","94.83","177.87"],"CWIP":["0.00","0.00","0.00","0.00","0.00","0.00","0.00","0.00","0.00","0.27","21.40","19.90"],"Investments":["81.45","68.79","81.45","87.75","136.73","99.43","113.77","117.62","117.65","102.79","99.94","99.66"],"Other Assets":["10.57","11.92","10.82","28.91","45.28","66.62","51.41","49.59","52.77","78.98","89.09","88.73"],"Total Assets":["218.82","198.07","157.72","215.15","271.09","242.49","232.61","225.68","220.57","222.63","305.26","386.16"]}},"cash_flow":{"headers":["Mar 2015","Mar 2016","Mar 2017","Mar 2018","Mar 2019","Mar 2020","Mar 2021","Mar 2022","Mar 2023","Mar 2024","Mar 2025","Mar 2026"],"rows":{"Cash from Operating Activity":["46.92","10.28","22.37","8.63","66.46","22.17","17.65","17.50","21.55","11.80","-3.59","65.37"],"Cash from Investing Activity":["-50.68","12.80","-12.59","-5.89","-47.51","2.52","-22.09","-0.42","0.24","-0.25","-51.50","-85.71"],"Cash from Financing Activity":["-1.16","-24.12","-9.95","-2.10","5.66","-19.74","-19.49","-16.95","-16.40","-5.68","74.13","25.10"],"Net Cash Flow":["-4.92","-1.03","-0.17","0.64","24.61","4.94","-23.94","0.13","5.40","5.87","19.04","4.76"],"Free Cash Flow":["46.88","10.28","22.37","8.63","66.44","25.80","17.65","17.50","21.09","12.41","-82.70","-22.86"],"CFO/OP":["139%","39%","93%","44%","301%","129%","93%","92%","109%","73%","-49%","437%"]}},"ratios":{"headers":["Mar 2015","Mar 2016","Mar 2017","Mar 2018","Mar 2019","Mar 2020","Mar 2021","Mar 2022","Mar 2023","Mar 2024","Mar 2025","Mar 2026"],"rows":{"Debtor Days":["15.78","0.95","0.14","0.45","1.02","0.74","0.00","6.43","0.71","39.77","45.94","9.00"],"Inventory Days":["","","","","","","","","0.00","","0.00","25.03"],"Days Payable":["","","","","","","","","","","","3,410.84"],"Cash Conversion Cycle":["15.78","0.95","0.14","0.45","1.02","0.74","0.00","6.43","0.71","39.77","45.94","-3,376.81"],"Working Capital Days":["-145.09","-30.93","-54.83","231.10","-412.03","282.80","444.77","440.76","367.00","766.23","362.89","-483.08"],"ROCE %":["13.07%","9.03%","6.19%","7.57%","6.74%","4.95%","5.80%","5.27%","5.74%","4.40%","2.37%","3.49%"]}},"shareholding":{"headers":["Sep 2020","Mar 2021","Sep 2021","Mar 2022","Sep 2022","Mar 2023","Sep 2023","Mar 2024","Sep 2024","Mar 2025","Sep 2025","Mar 2026"],"rows":{"Promoters":["69.85%","69.81%","69.81%","69.81%","69.81%","69.81%","69.75%","68.46%","67.85%","67.86%","67.86%","67.86%"],"Public":["30.15%","30.19%","30.19%","30.19%","30.19%","30.19%","30.26%","31.54%","32.15%","32.14%","32.13%","32.14%"],"No. of Shareholders":["334","327","483","1,046","1,087","1,060","1,098","1,469","2,278","2,367","2,412","2,307"]}},"insights":{"yearly":{"periods":["Mar 2016","Mar 2017","Mar 2018","Mar 2019","Mar 2020","Mar 2021","Mar 2022","Mar 2023","Mar 2024","Mar 2025"],"rows":[{"metric":"Capacity Utilization Factor (CUF) - Surendranagar Plant","unit":"%","values":{"Mar 2025":"xx.xxxx.xxxx.xxxx.xxxx.xxxx.xxxx.xxxx.xxxx.xxxx.xxxx.xxxx.xxxx.xxxx.xxxx.xxxx.xxxx.xxxx.xxxx.xxxx.xxxx,xxx,xxxxx,xxx,xxxxx,xxx,xxxxx,xxx,xxxxxx.xxUnlock insightsFree users can unlock up to 5 insights tables per month.Unlock"}}]}},"pros":["Stock is trading at 0.36 times its book value"],"cons":["Company has low interest coverage ratio.","The company has delivered a poor sales growth of 2.38% over past five years.","Company has a low return on equity of 0.94% over last 3 years.","Contingent liabilities of Rs.37.0 Cr.","Promoters have pledged 75.2% of their holding."],"analysis":{"trends":{"yearly":{"Sales":{"label":"Inconsistent","n":2,"unit":"yrs"},"Net Profit":{"label":"Decreasing","n":4,"unit":"yrs"},"OPM%":{"label":"Inconsistent","n":2,"unit":"yrs"},"EPS":{"label":"Decreasing","n":4,"unit":"yrs"},"Reserves":{"label":"Inconsistent","n":2,"unit":"yrs"},"Net Cash Flow":{"label":"Inconsistent","n":2,"unit":"yrs"},"Operating Cash Flow":{"label":"Inconsistent","n":2,"unit":"yrs"},"ROCE":{"label":"Inconsistent","n":2,"unit":"yrs"}},"quarterly":{"Sales":{"label":"Inconsistent","n":2,"unit":"qtrs"},"Net Profit":{"label":"Inconsistent","n":3,"unit":"qtrs"},"OPM%":{"label":"Inconsistent","n":2,"unit":"qtrs"},"EPS":{"label":"Inconsistent","n":3,"unit":"qtrs"},"Promoter Holding":{"label":"Inconsistent","n":1,"unit":"qtrs"}}},"cyclical":{"label":"CYCLICAL","positive_quarters":["Sep"],"negative_quarters":["Mar"]},"growth_insight":{"label":"PRICE-LED","long":"Insufficient data.","recent":"Recently, price growth exceeds profit growth by 103% \u2014 expectations running ahead of delivery."},"money_flow":{"label":"NEUTRAL","change":null,"note":"Insufficient shareholding history."},"dcf":{"ok":false,"reason":"no positive earnings"}}},"prices":{"ok":true,"ticker":"541445.BO","yearwise":[{"year":2018,"ret":-68.66},{"year":2019,"ret":-21.15},{"year":2020,"ret":89.7},{"year":2021,"ret":8.08},{"year":2022,"ret":12.37},{"year":2023,"ret":105.73},{"year":2024,"ret":32.61},{"year":2025,"ret":-38.28},{"year":2026,"ret":-31.89}],"heatmap":{"months":["Jan","Feb","Mar","Apr","May","Jun","Jul","Aug","Sep","Oct","Nov","Dec"],"rows":[{"year":2018,"vals":[null,null,null,null,null,null,-19.32,4.85,-9.93,-6.79,-4.0,-11.11],"annual":-39.4},{"year":2019,"vals":[-38.02,23.53,-23.67,36.54,-6.79,-3.08,-10.4,-22.58,4.17,15.8,-13.64,51.4],"annual":-21.13},{"year":2020,"vals":[-28.01,6.06,-41.52,16.86,-15.19,39.4,-21.2,19.57,100.45,-8.73,14.41,55.92],"annual":89.69},{"year":2021,"vals":[-23.26,7.8,54.04,20.22,-26.45,-1.11,-2.5,-14.87,2.41,13.24,-23.64,31.97],"annual":8.08},{"year":2022,"vals":[45.1,-22.02,-7.4,25.46,-16.18,-7.95,-1.02,-1.28,10.27,-1.06,24.2,-16.31],"annual":12.39},{"year":2023,"vals":[-6.54,-5.4,-4.02,-3.43,30.84,47.51,5.54,36.58,-20.07,1.95,-11.67,25.37],"annual":105.73},{"year":2024,"vals":[108.26,-19.17,-24.04,62.29,2.04,-2.5,-6.97,-4.18,-14.72,-3.66,-4.9,-7.79],"annual":32.59},{"year":2025,"vals":[-17.36,-29.64,-6.8,14.52,2.42,7.71,-14.97,-1.46,-4.57,-1.74,-17.53,39.11],"annual":-38.29},{"year":2026,"vals":[-24.41,-14.94,-9.28,49.46,-11.64,-11.58,null,null,null,null,null,null],"annual":-31.89}]},"risk":{"avg_weekly":0.5,"weekly_std":11.24,"ann_vol":81.04,"max_drawdown":-90.07,"pct_positive":44.12,"sharpe":0.32,"sortino":0.61},"technical":{"ret_3m":1.05,"excess_3m":-1.41,"ret_6m":3.95,"excess_6m":8.66,"ret_12m":-38.9,"excess_12m":-38.41,"rs_rating":36,"price":50.0,"above_50dma":false,"above_200dma":false,"golden_cross":false,"pos_52w":17.75,"dist_52w_high":-39.96,"benchmark":"Nifty 500"}},"signal":{"label":"SELL","composite":39,"confidence":"Medium","blocks":{"results":{"score":47,"reasons":["Sales +33% YoY","strong sales growth","sales up QoQ","Net profit -151% YoY","earnings growth decelerating"],"metrics":{"sales_yoy":32.7,"np_yoy":-150.9,"np_qoq":-775.0,"eps_yoy":-151.2,"accel":-53.3,"opm_exp":-6.8}},"technical":{"score":28,"reasons":["below 200-DMA"],"metrics":{"rs_rating":36,"excess_3m":-1.41,"excess_12m":-38.41,"above_200dma":false,"golden_cross":false,"pos_52w":17.75}},"fundamental":{"score":44,"reasons":["low ROE -0%"],"metrics":{"roe":-0.25,"roce":3.49,"dcf_mos":null}}},"weights":{"results":0.3,"technical":0.35,"fundamental":0.35},"reasons_pos":["Sales +33% YoY","strong sales growth","sales up QoQ"],"reasons_neg":["Net profit -151% YoY","earnings growth decelerating","low ROE -0%","below 200-DMA"],"ticker":"541445.BO","disclaimer":"Rules-based screen for research/education only \u2014 not personalized investment advice. Verify independently before any decision.","bias_check":{"risk":"LOW","principle":"Markets price expectations, not your conviction \u2014 weigh valuation, the macro and the data, not just the story.","flags":[{"level":"ok","title":"No major bias red-flags","note":"Valuation, momentum and the macro are broadly consistent with the verdict. Still do your own diligence.","lesson":"Being aware of your biases \u2014 not proximity \u2014 is the edge."}],"source":"Insider-Bias checklist"}}}