{"fundamental":{"code":"ATULAUTO","name":"Atul Auto Ltd","url":"https://www.screener.in/company/ATULAUTO/","overview":{"Market Cap":"\u20b9 1,265 Cr.","Current Price":"\u20b9 456","High / Low":"\u20b9 554 / 380","Stock P/E":"23.1","Book Value":"\u20b9 170","Dividend Yield":"0.00 %","ROCE":"16.2 %","ROE":"12.1 %","Face Value":"\u20b9 5.00"},"growth":{"Compounded Sales Growth":{"10 Years":"4%","5 Years":"22%","3 Years":"18%","TTM":"22%"},"Compounded Profit Growth":{"10 Years":"2%","5 Years":"48%","3 Years":"133%","TTM":"59%"},"Stock Price CAGR":{"10 Years":"-1%","5 Years":"18%","3 Years":"9%","1 Year":"-3%"},"Return on Equity":{"10 Years":"8%","5 Years":"4%","3 Years":"8%","Last Year":"12%"}},"quarters":{"headers":["Jun 2023","Sep 2023","Dec 2023","Mar 2024","Jun 2024","Sep 2024","Dec 2024","Mar 2025","Jun 2025","Sep 2025","Dec 2025","Mar 2026"],"rows":{"Sales":["50","139","146","145","127","165","175","180","137","181","214","230"],"OPM":["-14%","11%","8%","7%","7%","9%","9%","9%","7%","10%","13%","11%"],"Net Profit":["-8","9","7","6","5","10","10","11","5","12","18","17"],"EPS":["-3.08","3.07","2.44","2.23","1.64","3.43","3.60","3.81","1.77","4.27","6.54","6.27"]}},"profit_loss":{"headers":["Mar 2015","Mar 2016","Mar 2017","Mar 2018","Mar 2019","Mar 2020","Mar 2021","Mar 2022","Mar 2023","Mar 2024","Mar 2025","Mar 2026"],"rows":{"Sales":["493","531","475","556","667","625","296","294","475","480","646","786"],"Expenses":["435","455","416","483","585","554","304","315","452","450","589","704"],"Operating Profit":["58","76","60","73","81","71","-8","-22","23","30","57","82"],"OPM %":["12%","14%","13%","13%","12%","11%","-3%","-7%","5%","6%","9%","10%"],"Other Income":["8","1","2","3","7","3","2","2","3","5","5","6"],"Interest":["1","1","1","0","1","1","1","4","6","2","0","1"],"Depreciation":["6","5","5","5","6","6","7","9","14","15","15","16"],"Profit before tax":["59","72","56","69","82","67","-13","-32","6","18","46","72"],"Tax %":["32%","34%","34%","33%","35%","22%","-23%","-23%","26%","24%","25%","25%"],"Net Profit":["41","47","37","46","53","52","-10","-25","4","13","35","54"],"EPS in Rs":["18.49","21.60","16.88","21.05","24.21","23.88","-4.65","-11.33","1.84","4.85","12.48","19.35"],"Dividend Payout %":["28%","25%","25%","25%","17%","6%","0%","0%","0%","0%","0%","16%"]}},"balance_sheet":{"headers":["Mar 2015","Mar 2016","Mar 2017","Mar 2018","Mar 2019","Mar 2020","Mar 2021","Mar 2022","Mar 2023","Mar 2024","Mar 2025","Mar 2026"],"rows":{"Equity Capital":["11","11","11","11","11","11","11","11","12","14","14","14"],"Reserves":["110","143","173","208","248","292","282","258","319","387","422","457"],"Borrowings":["0","0","0","0","0","1","16","81","36","0","0","0"],"Other Liabilities":["56","67","61","80","95","72","72","69","75","69","105","126"],"Total Liabilities":["177","222","245","299","353","376","381","419","442","471","540","597"],"Fixed Assets":["79","85","87","87","94","93","90","198","236","230","228","222"],"CWIP":["0","3","3","5","37","117","148","43","1","0","1","3"],"Investments":["1","1","24","59","23","15","29","68","85","110","113","166"],"Other Assets":["97","133","131","149","200","152","113","110","120","131","198","206"],"Total Assets":["177","222","245","299","353","376","381","419","442","471","540","597"]}},"cash_flow":{"headers":["Mar 2015","Mar 2016","Mar 2017","Mar 2018","Mar 2019","Mar 2020","Mar 2021","Mar 2022","Mar 2023","Mar 2024","Mar 2025","Mar 2026"],"rows":{"Cash from Operating Activity":["28","11","71","26","35","57","52","-19","12","13","60","65"],"Cash from Investing Activity":["-36","-10","-29","-39","-28","-58","-60","-44","-20","-25","-55","-75"],"Cash from Financing Activity":["-11","-14","-14","-11","-15","-7","14","61","6","20","-1","14"],"Net Cash Flow":["-19","-13","28","-24","-7","-8","6","-2","-2","7","4","4"],"Free Cash Flow":["-8","1","63","19","-25","-16","13","-29","8","6","44","54"],"CFO/OP":["77%","47%","152%","68%","77%","107%","-686%","86%","51%","40%","106%","99%"]}},"ratios":{"headers":["Mar 2015","Mar 2016","Mar 2017","Mar 2018","Mar 2019","Mar 2020","Mar 2021","Mar 2022","Mar 2023","Mar 2024","Mar 2025","Mar 2026"],"rows":{"Debtor Days":["24","52","36","51","55","46","29","26","21","36","33","32"],"Inventory Days":["26","33","38","42","42","39","78","76","53","54","53","49"],"Days Payable":["26","34","38","45","43","32","71","63","44","39","47","50"],"Cash Conversion Cycle":["23","51","37","48","54","53","36","39","30","51","39","31"],"Working Capital Days":["8","37","24","35","40","38","22","5","14","36","49","56"],"ROCE %":["54%","52%","32%","34%","33%","24%","-4%","-9%","3%","5%","11%","16%"]}},"shareholding":{"headers":["Jun 2023","Sep 2023","Dec 2023","Mar 2024","Jun 2024","Sep 2024","Dec 2024","Mar 2025","Jun 2025","Sep 2025","Dec 2025","Mar 2026"],"rows":{"Promoters":["46.46%","42.74%","42.74%","42.74%","42.74%","42.74%","42.74%","42.74%","42.74%","42.70%","42.70%","42.70%"],"FIIs":["0.43%","0.46%","0.49%","0.48%","0.59%","0.58%","0.63%","0.69%","0.37%","0.01%","0.38%","0.84%"],"DIIs":["0.76%","0.41%","0.41%","0.41%","0.41%","0.31%","0.13%","0.13%","0.13%","0.10%","0.10%","0.10%"],"Public":["52.35%","56.40%","56.39%","56.39%","56.28%","56.39%","56.52%","56.44%","56.76%","57.19%","56.83%","56.37%"],"No. of Shareholders":["44,433","46,849","49,414","49,815","49,228","57,803","58,649","59,882","60,504","63,289","61,382","59,046"]}},"insights":{"yearly":{"periods":["Mar 2014","Mar 2015","Mar 2016","Mar 2017","Mar 2018","Mar 2019","Mar 2020","Mar 2021","Mar 2022","Mar 2023","Mar 2024","Mar 2025"],"rows":[{"metric":"Capacity Utilization","unit":"%","values":{"Mar 2025":"xx.xxxx.xxxx.xxxx.xxxx.xxxx.xxxx.xxxx.xxxx.xxxx.xxxx.xxxx.xxxx,xxxxx,xxxxx,xxxxx,xxxxx,xxxxx,xxxxx,xxxxx,xxxxx,xxxxx,xxxxx,xxxxx,xxxxx,xxxxx,xxxxx,xxxxx,xxxxx,xxxxx,xxxxx,xxxxx,xxxxxx,xxxxxx,xxxxxx,xxxxxxxxxxxxxxxxxxxxxxxxxxxxxxx,xxxxUnlock insightsFree users can unlock up to 5 insights tables per month.Unlock"}}]}},"pros":["Company is almost debt free.","Company has delivered good profit growth of 48.0% CAGR over last 5 years"],"cons":["Stock is trading at 2.69 times its book value","Company has a low return on equity of 8.23% over last 3 years.","Promoter holding has decreased over last 3 years: -6.78%"],"analysis":{"trends":{"yearly":{"Sales":{"label":"Increasing","n":5,"unit":"yrs"},"Net Profit":{"label":"Increasing","n":5,"unit":"yrs"},"OPM%":{"label":"Increasing","n":5,"unit":"yrs"},"EPS":{"label":"Increasing","n":5,"unit":"yrs"},"Reserves":{"label":"Increasing","n":5,"unit":"yrs"},"Net Cash Flow":{"label":"Inconsistent","n":1,"unit":"yrs"},"Operating Cash Flow":{"label":"Increasing","n":5,"unit":"yrs"},"ROCE":{"label":"Increasing","n":5,"unit":"yrs"}},"quarterly":{"Sales":{"label":"Increasing","n":4,"unit":"qtrs"},"Net Profit":{"label":"Inconsistent","n":2,"unit":"qtrs"},"OPM%":{"label":"Inconsistent","n":2,"unit":"qtrs"},"EPS":{"label":"Inconsistent","n":2,"unit":"qtrs"},"Promoter Holding":{"label":"Inconsistent","n":1,"unit":"qtrs"},"Institutional Holding":{"label":"Inconsistent","n":3,"unit":"qtrs"}}},"cyclical":{"label":"CYCLICAL","positive_quarters":["Sep"],"negative_quarters":["Mar","Jun","Dec"]},"growth_insight":{"label":"FUNDAMENTALS-LED","long":"Profit grew 48% vs price 18% (5Y) \u2014 fundamentals outpacing the stock; potentially undervalued.","recent":"Recently, profit growth exceeds 1-year price growth by 62%, the company is starting to outperform expectations."},"money_flow":{"label":"POSITIVE MONEY FLOW","change":0.46,"note":"Tracks institutional (FII+DII) holding change \u2014 proxy for smart-money flow."},"dcf":{"ok":true,"inputs":{"earnings":54,"growth":18.0,"discount":10,"terminal_growth":2,"years":10,"terminal_multiple":12.8},"dcf":{"rows":[{"year":1,"earnings":64,"growth":18.0,"pv":58},{"year":2,"earnings":75,"growth":18.0,"pv":62},{"year":3,"earnings":89,"growth":18.0,"pv":67},{"year":4,"earnings":105,"growth":18.0,"pv":72},{"year":5,"earnings":124,"growth":18.0,"pv":77},{"year":6,"earnings":146,"growth":18.0,"pv":82},{"year":7,"earnings":172,"growth":18.0,"pv":88},{"year":8,"earnings":203,"growth":18.0,"pv":95},{"year":9,"earnings":240,"growth":18.0,"pv":102},{"year":10,"earnings":283,"growth":18.0,"pv":109}],"pv_1_n":811,"terminal_year_cf":288,"terminal_value":3603,"pv_terminal":1389,"effective_multiple":12.8,"total_pv":2200},"reverse":{"rows":[{"year":1,"earnings":60,"growth":10.4,"pv":54},{"year":2,"earnings":66,"growth":10.4,"pv":54},{"year":3,"earnings":73,"growth":10.4,"pv":55},{"year":4,"earnings":80,"growth":10.4,"pv":55},{"year":5,"earnings":89,"growth":10.4,"pv":55},{"year":6,"earnings":98,"growth":10.4,"pv":55},{"year":7,"earnings":108,"growth":10.4,"pv":55},{"year":8,"earnings":119,"growth":10.4,"pv":56},{"year":9,"earnings":132,"growth":10.4,"pv":56},{"year":10,"earnings":145,"growth":10.4,"pv":56}],"pv_1_n":551,"terminal_year_cf":148,"terminal_value":1852,"pv_terminal":714,"effective_multiple":12.8,"total_pv":1265,"implied_growth":10.4},"intrinsic_total":2200,"intrinsic_per_share":793,"current_price":456.0,"market_cap":1265.0,"margin_of_safety":42.5}}},"prices":{"ok":true,"ticker":"ATULAUTO.NS","yearwise":[{"year":2013,"ret":62.05},{"year":2014,"ret":370.58},{"year":2015,"ret":-17.8},{"year":2016,"ret":-24.81},{"year":2017,"ret":13.3},{"year":2018,"ret":-35.51},{"year":2019,"ret":-12.16},{"year":2020,"ret":-26.97},{"year":2021,"ret":3.5},{"year":2022,"ret":47.35},{"year":2023,"ret":103.59},{"year":2024,"ret":1.17},{"year":2025,"ret":-24.02},{"year":2026,"ret":3.62}],"heatmap":{"months":["Jan","Feb","Mar","Apr","May","Jun","Jul","Aug","Sep","Oct","Nov","Dec"],"rows":[{"year":2013,"vals":[null,null,null,null,null,null,-0.53,-13.7,18.41,34.01,22.31,-1.16],"annual":64.67},{"year":2014,"vals":[-1.63,-0.72,28.53,5.41,-0.44,38.47,18.81,11.89,4.93,8.85,32.31,28.43],"annual":370.63},{"year":2015,"vals":[-9.39,-8.18,-1.06,-12.42,-5.89,5.65,-4.27,-10.45,11.6,5.66,7.32,5.73],"annual":-17.78},{"year":2016,"vals":[-8.55,-15.29,21.4,2.24,-7.15,0.5,-4.73,-4.94,7.77,1.47,-6.89,-9.12],"annual":-24.81},{"year":2017,"vals":[3.51,-1.34,12.1,-7.99,-2.36,-5.94,9.21,6.8,1.51,-2.42,-6.4,8.31],"annual":13.3},{"year":2018,"vals":[-10.23,3.74,3.5,0.69,-3.57,-8.58,4.53,-5.81,-12.98,1.99,-3.85,-10.29],"annual":-35.51},{"year":2019,"vals":[5.05,1.77,8.97,-4.04,-3.44,-14.37,-15.01,-7.22,7.34,2.67,7.76,1.47],"annual":-12.17},{"year":2020,"vals":[-0.06,-10.61,-38.18,21.46,-0.86,0.89,-7.97,13.83,-4.4,-7.58,8.81,8.06],"annual":-26.98},{"year":2021,"vals":[-3.69,7.41,-6.22,2.38,5.9,-3.22,15.54,-7.91,7.82,11.76,-12.93,-8.91],"annual":3.51},{"year":2022,"vals":[6.06,-12.14,-9.14,14.9,-6.85,-1.88,0.91,13.53,-3.27,52.79,10.22,-11.2],"annual":47.35},{"year":2023,"vals":[14.4,7.23,-9.08,21.98,-6.32,-2.92,5.62,61.05,1.72,1.69,0.52,-6.98],"annual":103.56},{"year":2024,"vals":[-0.59,-5.08,-11.87,10.79,-3.1,22.75,15.62,-12.52,0.62,-4.84,-6.62,2.1],"annual":1.19},{"year":2025,"vals":[-10.87,-14.61,0.25,5.17,4.2,-4.98,-3.39,-4.05,11.38,1.92,-2.24,-7.03],"annual":-24.02},{"year":2026,"vals":[-8.79,23.59,-22.91,27.76,-1.53,-5.23,null,null,null,null,null,null],"annual":3.61}]},"risk":{"avg_weekly":0.43,"weekly_std":6.11,"ann_vol":44.03,"max_drawdown":-82.02,"pct_positive":46.01,"sharpe":0.51,"sortino":1.06},"technical":{"ret_3m":5.67,"excess_3m":3.21,"ret_6m":4.81,"excess_6m":9.51,"ret_12m":-6.7,"excess_12m":-6.2,"rs_rating":58,"price":455.7,"above_50dma":false,"above_200dma":false,"golden_cross":true,"pos_52w":46.95,"dist_52w_high":-15.42,"benchmark":"Nifty 500"}},"signal":{"label":"BUY","composite":76,"confidence":"Medium","blocks":{"results":{"score":84,"reasons":["Sales +28% YoY","strong sales growth","Net profit +55% YoY","profit growth >20% YoY","sales up QoQ","margins expanding","earnings growth decelerating"],"metrics":{"sales_yoy":27.8,"np_yoy":54.5,"np_qoq":-5.6,"eps_yoy":64.6,"accel":-25.5,"opm_exp":2.0}},"technical":{"score":56,"reasons":["+3% vs Nifty 500 (3M)","below 200-DMA","golden cross (50>200)"],"metrics":{"rs_rating":58,"excess_3m":3.21,"excess_12m":-6.2,"above_200dma":false,"golden_cross":true,"pos_52w":46.95}},"fundamental":{"score":90,"reasons":["multi-year sales uptrend","multi-year profit uptrend","rising EPS trend","ROCE 16%","DCF margin of safety 42%","institutional inflow"],"metrics":{"roe":12.1,"roce":16.2,"dcf_mos":42.5}}},"weights":{"results":0.3,"technical":0.35,"fundamental":0.35},"reasons_pos":["Sales +28% YoY","strong sales growth","Net profit +55% YoY","profit growth >20% YoY","sales up QoQ","margins expanding"],"reasons_neg":["earnings growth decelerating","below 200-DMA"],"ticker":"ATULAUTO.NS","disclaimer":"Rules-based screen for research/education only \u2014 not personalized investment advice. Verify independently before any decision.","bias_check":{"risk":"LOW","principle":"Markets price expectations, not your conviction \u2014 weigh valuation, the macro and the data, not just the story.","flags":[{"level":"ok","title":"Sector tailwind","note":"Capital Goods is in a TAILWIND (tailwind score +0.64) \u2014 the macro backdrop supports the setup.","lesson":"Focus on cycles and change, not insider chatter (the author's actual edge)."},{"level":"info","title":"Size it \u2014 don't fall in love","note":"Even a clean BUY deserves a position cap and an exit plan. Concentrated conviction (loyalty to one name) is how good theses become big drawdowns.","lesson":"Amazon: a great company held with no diversification became the biggest single loss."}],"source":"Insider-Bias checklist"}}}