{"fundamental":{"code":"AVSL","name":"AVSL Industries Ltd","url":"https://www.screener.in/company/AVSL/","overview":{"Market Cap":"\u20b9 63.8 Cr.","Current Price":"\u20b9 120","High / Low":"\u20b9 131 / 120","Stock P/E":"28.4","Book Value":"\u20b9 75.0","Dividend Yield":"0.00 %","ROCE":"9.03 %","ROE":"5.78 %","Face Value":"\u20b9 10.0"},"growth":{"Compounded Sales Growth":{"10 Years":"8%","5 Years":"13%","3 Years":"14%","TTM":"8%"},"Compounded Profit Growth":{"10 Years":"28%","5 Years":"-17%","3 Years":"47%","TTM":"-10%"},"Stock Price CAGR":{"10 Years":"%","5 Years":"30%","3 Years":"-2%","1 Year":"-7%"},"Return on Equity":{"10 Years":"12%","5 Years":"8%","3 Years":"6%","Last Year":"6%"}},"quarters":{"headers":["Sep 2020","Mar 2021","Sep 2021","Mar 2022","Sep 2022","Mar 2023","Sep 2023","Mar 2024","Sep 2024","Mar 2025","Sep 2025","Mar 2026"],"rows":{"Sales":["36","46","46","54","51","51","61","76","69","70","77","73"],"OPM":["6%","12%","10%","9%","3%","4%","3%","7%","16%","7%","16%","6%"],"Net Profit":["2","4","3","3","0","0","0","2","1","1","1","1"],"EPS":["4.22","6.96","5.40","5.65","0.30","0.66","0.86","3.34","2.08","2.66","1.91","1.69"]}},"profit_loss":{"headers":["Mar 2015","Mar 2016","Mar 2017","Mar 2018","Mar 2019","Mar 2020","Mar 2021","Mar 2022","Mar 2023","Mar 2024","Mar 2025","Mar 2026"],"rows":{"Sales":["14","67","78","102","84","82","82","100","101","137","139","150"],"Expenses":["14","68","78","98","81","76","75","91","98","130","131","140"],"Operating Profit":["-0","-1","0","3","3","6","7","10","4","7","8","10"],"OPM %":["-0%","-1%","0%","3%","4%","8%","9%","10%","4%","5%","6%","6%"],"Other Income":["0","2","2","1","2","1","3","1","1","1","2","1"],"Interest":["0","0","1","1","1","1","1","1","2","3","4","4"],"Depreciation":["0","0","0","0","0","1","1","1","2","2","3","3"],"Profit before tax":["0","0","1","3","3","6","8","8","1","3","3","3"],"Tax %":["40%","32%","37%","31%","33%","29%","27%","27%","9%","30%","26%","28%"],"Net Profit":["0","0","1","2","2","4","6","6","1","2","3","2"],"EPS in Rs":["0.93","0.49","1.35","4.37","4.26","7.90","10.97","11.05","0.96","4.20","4.75","4.00"],"Dividend Payout %":["0%","0%","0%","0%","0%","0%","0%","0%","0%","0%","0%","0%"]}},"balance_sheet":{"headers":["Mar 2015","Mar 2016","Mar 2017","Mar 2018","Mar 2019","Mar 2020","Mar 2021","Mar 2022","Mar 2023","Mar 2024","Mar 2025","Mar 2026"],"rows":{"Equity Capital":["0.32","4","5","5","5","5","5","5","5","5","5","5"],"Reserves":["3","2","7","9","11","15","21","27","28","30","32","35"],"Borrowings":["0","9","12","13","7","19","20","23","34","35","40","40"],"Other Liabilities":["11","24","22","23","24","28","20","20","9","20","20","24"],"Total Liabilities":["15","39","46","51","48","68","67","76","76","91","98","104"],"Fixed Assets":["3","3","4","5","6","19","22","26","29","31","35","35"],"CWIP":["0","0","0","0","0","0","0","0","0","0","0","0"],"Investments":["0","0","0","0","0","0","0","0","0","0","0","0"],"Other Assets":["12","37","42","46","42","48","45","50","48","60","63","69"],"Total Assets":["15","39","46","51","48","68","67","76","76","91","98","104"]}},"cash_flow":{"headers":["Mar 2015","Mar 2016","Mar 2017","Mar 2018","Mar 2019","Mar 2020","Mar 2021","Mar 2022","Mar 2023","Mar 2024","Mar 2025","Mar 2026"],"rows":{"Cash from Operating Activity":["1","-10","-6","3","8","3","4","4","-5","6","6","7"],"Cash from Investing Activity":["-0","0","-2","-2","-2","-14","-4","-5","-4","-4","-7","-4"],"Cash from Financing Activity":["0","10","7","0","-7","11","0","1","9","-2","2","-3"],"Net Cash Flow":["1","-0","-0","1","-1","-1","1","-0","-0","1","0","0"],"Free Cash Flow":["1","-10","-8","2","6","-11","0","-2","-10","2","-1","3"],"CFO/OP":["-2,240%","1,198%","-1,832%","102%","288%","76%","82%","59%","-144%","105%","88%","72%"]}},"ratios":{"headers":["Mar 2015","Mar 2016","Mar 2017","Mar 2018","Mar 2019","Mar 2020","Mar 2021","Mar 2022","Mar 2023","Mar 2024","Mar 2025","Mar 2026"],"rows":{"Debtor Days":["114","123","148","140","136","142","127","99","90","100","95","91"],"Inventory Days":["157","68","25","14","36","54","60","77","82","64","59","82"],"Days Payable":["311","140","103","85","115","139","88","75","27","52","51","62"],"Cash Conversion Cycle":["-40","51","70","69","57","57","98","101","145","112","103","110"],"Working Capital Days":["-17","12","31","28","40","32","36","29","16","10","7","13"],"ROCE %":["2%","7%","11%","18%","18%","22%","21%","19%","5%","9%","9%","9%"]}},"shareholding":{"headers":["Sep 2020","Mar 2021","Sep 2021","Mar 2022","Sep 2022","Mar 2023","Sep 2023","Mar 2024","Sep 2024","Mar 2025","Sep 2025","Mar 2026"],"rows":{"Promoters":["69.52%","70.25%","71.15%","71.65%","71.65%","71.65%","71.65%","71.88%","71.88%","71.99%","71.99%","71.99%"],"Public":["30.49%","29.76%","28.85%","28.34%","28.35%","28.34%","28.35%","28.12%","28.12%","28.01%","28.01%","28.01%"],"No. of Shareholders":["104","99","98","94","96","95","103","102","102","102","98","97"]}},"insights":{"yearly":{"periods":["Mar 2014","Mar 2015","Mar 2016","Mar 2019","Mar 2020","Mar 2021","Mar 2022","Mar 2023","Mar 2024"],"rows":[{"metric":"Number of Employees","unit":"Count","values":{"Mar 2024":"xxxxxxxxxxxxxxxxxxxxxxx.xxx.xxx.xxx.xxx,xxxx,xxxx,xxxx,xxx.xxx,xxx.xxx,xxx.xxUnlock insightsFree users can unlock up to 5 insights tables per month.Unlock"}}]}},"pros":[],"cons":["Though the company is reporting repeated profits, it is not paying out dividend","Company has low interest coverage ratio.","Company has a low return on equity of 6.39% over last 3 years."],"analysis":{"trends":{"yearly":{"Sales":{"label":"Increasing","n":6,"unit":"yrs"},"Net Profit":{"label":"Inconsistent","n":2,"unit":"yrs"},"OPM%":{"label":"Inconsistent","n":1,"unit":"yrs"},"EPS":{"label":"Inconsistent","n":2,"unit":"yrs"},"Reserves":{"label":"Increasing","n":11,"unit":"yrs"},"Net Cash Flow":{"label":"Inconsistent","n":1,"unit":"yrs"},"Operating Cash Flow":{"label":"Inconsistent","n":2,"unit":"yrs"},"ROCE":{"label":"Inconsistent","n":1,"unit":"yrs"}},"quarterly":{"Sales":{"label":"Inconsistent","n":2,"unit":"qtrs"},"Net Profit":{"label":"Inconsistent","n":1,"unit":"qtrs"},"OPM%":{"label":"Inconsistent","n":2,"unit":"qtrs"},"EPS":{"label":"Inconsistent","n":3,"unit":"qtrs"},"Promoter Holding":{"label":"Inconsistent","n":1,"unit":"qtrs"}}},"cyclical":{"label":"NON-CYCLICAL","positive_quarters":[],"negative_quarters":["Mar","Sep"]},"growth_insight":{"label":"PRICE-LED","long":"Price grew 30% vs profit -17% (5Y) \u2014 stock ahead of fundamentals; watch valuation.","recent":"Recently, price growth exceeds profit growth by 3% \u2014 expectations running ahead of delivery."},"money_flow":{"label":"NEUTRAL","change":null,"note":"Insufficient shareholding history."},"dcf":{"ok":true,"inputs":{"earnings":2,"growth":0.0,"discount":10,"terminal_growth":2,"years":10,"terminal_multiple":12.8},"dcf":{"rows":[{"year":1,"earnings":2,"growth":0.0,"pv":2},{"year":2,"earnings":2,"growth":0.0,"pv":2},{"year":3,"earnings":2,"growth":0.0,"pv":2},{"year":4,"earnings":2,"growth":0.0,"pv":1},{"year":5,"earnings":2,"growth":0.0,"pv":1},{"year":6,"earnings":2,"growth":0.0,"pv":1},{"year":7,"earnings":2,"growth":0.0,"pv":1},{"year":8,"earnings":2,"growth":0.0,"pv":1},{"year":9,"earnings":2,"growth":0.0,"pv":1},{"year":10,"earnings":2,"growth":0.0,"pv":1}],"pv_1_n":12,"terminal_year_cf":2,"terminal_value":26,"pv_terminal":10,"effective_multiple":12.8,"total_pv":22},"reverse":{"rows":[{"year":1,"earnings":2,"growth":14.57,"pv":2},{"year":2,"earnings":3,"growth":14.57,"pv":2},{"year":3,"earnings":3,"growth":14.57,"pv":2},{"year":4,"earnings":3,"growth":14.57,"pv":2},{"year":5,"earnings":4,"growth":14.57,"pv":2},{"year":6,"earnings":5,"growth":14.57,"pv":3},{"year":7,"earnings":5,"growth":14.57,"pv":3},{"year":8,"earnings":6,"growth":14.57,"pv":3},{"year":9,"earnings":7,"growth":14.57,"pv":3},{"year":10,"earnings":8,"growth":14.57,"pv":3}],"pv_1_n":25,"terminal_year_cf":8,"terminal_value":99,"pv_terminal":38,"effective_multiple":12.8,"total_pv":64,"implied_growth":14.57},"intrinsic_total":22,"intrinsic_per_share":41,"current_price":120.0,"market_cap":63.8,"margin_of_safety":-190.0}}},"prices":{"ok":true,"ticker":"AVSL.NS","yearwise":[{"year":2017,"ret":-14.56},{"year":2018,"ret":26.68},{"year":2019,"ret":5.98},{"year":2020,"ret":-23.08},{"year":2021,"ret":7.0},{"year":2022,"ret":295.79},{"year":2023,"ret":14.68},{"year":2024,"ret":3.47},{"year":2025,"ret":-16.42},{"year":2026,"ret":-5.0}],"heatmap":{"months":["Jan","Feb","Mar","Apr","May","Jun","Jul","Aug","Sep","Oct","Nov","Dec"],"rows":[{"year":2017,"vals":[null,null,null,5.37,5.95,-8.29,-7.87,0.0,1.27,-15.62,-2.22,10.04],"annual":-13.27},{"year":2018,"vals":[-3.61,1.79,0.0,-1.75,0.0,0.0,5.71,21.62,-11.11,13.28,0.69,0.82],"annual":26.69},{"year":2019,"vals":[-4.89,0.0,-2.86,0.0,-5.88,5.31,-3.86,0.15,0.15,0.0,20.0,0.0],"annual":5.97},{"year":2020,"vals":[0.0,-10.26,2.86,19.72,0.0,0.0,0.0,0.0,-19.95,29.13,-32.66,0.0],"annual":-23.08},{"year":2021,"vals":[8.17,3.54,0.0,-4.46,0.0,0.0,0.0,0.0,0.0,0.0,0.0,0.0],"annual":7.0},{"year":2022,"vals":[15.58,0.0,4.99,21.05,21.31,0.0,37.59,-0.25,47.52,4.49,5.0,0.0],"annual":295.83},{"year":2023,"vals":[10.23,0.0,3.53,0.0,-11.55,-14.89,-18.28,0.06,9.92,56.73,-0.26,-4.99],"annual":14.68},{"year":2024,"vals":[4.98,15.07,-15.34,0.5,-4.97,42.55,-5.0,-6.59,3.14,-5.33,-9.73,-4.98],"annual":3.48},{"year":2025,"vals":[0.0,4.81,0.0,-18.23,0.0,0.0,1.59,-4.76,-4.0,0.0,0.0,5.0],"annual":-16.42},{"year":2026,"vals":[-5.0,0.0,0.0,0.0,0.0,0.0,null,null,null,null,null,null],"annual":-5.0}]},"risk":{"avg_weekly":0.38,"weekly_std":5.03,"ann_vol":36.28,"max_drawdown":-44.82,"pct_positive":13.07,"sharpe":0.54,"sortino":0.65},"technical":{"ret_3m":0.0,"excess_3m":-2.46,"ret_6m":-5.0,"excess_6m":-0.29,"ret_12m":-7.35,"excess_12m":-6.86,"rs_rating":43,"price":119.7,"above_50dma":false,"above_200dma":false,"golden_cross":false,"pos_52w":0.0,"dist_52w_high":-8.8,"benchmark":"Nifty 500"}},"signal":{"label":"SELL","composite":32,"confidence":"High","blocks":{"results":{"score":28,"reasons":["Net profit -50% YoY","Sales -4% YoY"],"metrics":{"sales_yoy":-3.9,"np_yoy":-50.0,"np_qoq":0.0,"eps_yoy":-49.4,"accel":null,"opm_exp":-1.0}},"technical":{"score":29,"reasons":["below 200-DMA","near 52-week low"],"metrics":{"rs_rating":43,"excess_3m":-2.46,"excess_12m":-6.86,"above_200dma":false,"golden_cross":false,"pos_52w":0.0}},"fundamental":{"score":38,"reasons":["multi-year sales uptrend","low ROE 6%","DCF overvalued (-190%)"],"metrics":{"roe":5.78,"roce":9.03,"dcf_mos":-190.0}}},"weights":{"results":0.3,"technical":0.35,"fundamental":0.35},"reasons_pos":["multi-year sales uptrend","near 52-week low"],"reasons_neg":["Net profit -50% YoY","Sales -4% YoY","low ROE 6%","DCF overvalued (-190%)","below 200-DMA"],"ticker":"AVSL.NS","disclaimer":"Rules-based screen for research/education only \u2014 not personalized investment advice. Verify independently before any decision.","bias_check":{"risk":"ELEVATED","principle":"Markets price expectations, not your conviction \u2014 weigh valuation, the macro and the data, not just the story.","flags":[{"level":"warn","title":"Valuation blind-spot","note":"Rich valuation \u2014 P/E 28, P/B 1.6, DCF overvalued 190%. Even with a decent story, a lot of optimism is already in the price.","lesson":"KPIT: strong EV/software story, valuation ignored \u2192 about \u221230%."},{"level":"ok","title":"Sector tailwind","note":"Capital Goods is in a TAILWIND (tailwind score +0.64) \u2014 the macro backdrop supports the setup.","lesson":"Focus on cycles and change, not insider chatter (the author's actual edge)."}],"source":"Insider-Bias checklist"}}}