{"fundamental":{"code":"SCI","name":"Shipping Corporation of India Ltd","url":"https://www.screener.in/company/SCI/","overview":{"Market Cap":"\u20b9 13,837 Cr.","Current Price":"\u20b9 297","High / Low":"\u20b9 369 / 195","Stock P/E":"10.4","Book Value":"\u20b9 182","Dividend Yield":"2.22 %","ROCE":"14.8 %","ROE":"16.3 %","Face Value":"\u20b9 10.0"},"growth":{"Compounded Sales Growth":{"10 Years":"4%","5 Years":"9%","3 Years":"0%","TTM":"3%"},"Compounded Profit Growth":{"10 Years":"6%","5 Years":"17%","3 Years":"19%","TTM":"65%"},"Stock Price CAGR":{"10 Years":"19%","5 Years":"28%","3 Years":"42%","1 Year":"31%"},"Return on Equity":{"10 Years":"8%","5 Years":"12%","3 Years":"12%","Last Year":"16%"}},"quarters":{"headers":["Jun 2023","Sep 2023","Dec 2023","Mar 2024","Jun 2024","Sep 2024","Dec 2024","Mar 2025","Jun 2025","Sep 2025","Dec 2025","Mar 2026"],"rows":{"Sales":["1,200","1,093","1,341","1,412","1,514","1,451","1,303","1,325","1,316","1,338","1,611","1,513"],"OPM":["30%","22%","31%","29%","34%","37%","27%","28%","37%","31%","42%","41%"],"Net Profit":["147","41","132","292","287","290","65","172","343","176","393","414"],"EPS":["3.16","0.87","2.83","6.27","6.16","6.23","1.39","3.70","7.37","3.78","8.45","8.88"]}},"profit_loss":{"headers":["Mar 2015","Mar 2016","Mar 2017","Mar 2018","Mar 2019","Mar 2020","Mar 2021","Mar 2022","Mar 2023","Mar 2024","Mar 2025","Mar 2026"],"rows":{"Sales":["4,186","4,050","3,447","3,469","3,873","4,425","3,703","4,988","5,794","5,046","5,592","5,778"],"Expenses":["3,361","2,688","2,667","2,793","3,160","3,283","2,544","3,455","4,234","3,622","3,824","3,585"],"Operating Profit":["826","1,362","780","677","713","1,143","1,159","1,533","1,560","1,424","1,768","2,193"],"OPM %":["20%","34%","23%","20%","18%","26%","31%","31%","27%","28%","32%","38%"],"Other Income":["401","165","145","143","232","243","126","97","111","215","193","440"],"Interest":["180","195","174","180","362","367","22","161","185","171","187","173"],"Depreciation":["770","542","566","610","658","671","628","635","753","889","951","1,064"],"Profit before tax":["276","789","186","29","-75","348","635","834","733","578","822","1,396"],"Tax %":["27%","5%","23%","-761%","63%","13%","3%","5%","-9%","-6%","1%","5%"],"Net Profit":["201","753","142","254","-122","302","618","790","800","612","814","1,326"],"EPS in Rs":["4.31","16.17","3.05","5.45","-2.62","6.49","13.27","16.96","17.18","13.14","17.48","28.47"],"Dividend Payout %":["0%","0%","0%","0%","0%","12%","2%","2%","3%","4%","38%","16%"]}},"balance_sheet":{"headers":["Mar 2015","Mar 2016","Mar 2017","Mar 2018","Mar 2019","Mar 2020","Mar 2021","Mar 2022","Mar 2023","Mar 2024","Mar 2025","Mar 2026"],"rows":{"Equity Capital":["466","466","466","466","466","466","466","466","466","466","466","466"],"Reserves":["6,068","6,258","6,367","6,632","6,515","6,832","7,436","5,111","5,906","6,498","7,278","8,023"],"Borrowings":["6,833","5,845","5,492","5,585","5,277","4,767","3,679","3,200","2,605","2,914","2,228","2,679"],"Other Liabilities":["1,562","2,148","2,162","1,686","1,896","1,668","1,556","1,684","1,936","1,646","1,160","1,539"],"Total Liabilities":["14,929","14,717","14,487","14,369","14,155","13,733","13,137","10,461","10,912","11,523","11,132","12,707"],"Fixed Assets":["11,444","11,827","11,411","11,348","11,119","10,653","10,174","7,624","7,403","7,004","6,711","7,198"],"CWIP":["491","0","27","8","8","3","33","58","34","42","4","5"],"Investments":["90","66","75","131","77","77","77","78","79","79","286","196"],"Other Assets":["2,903","2,824","2,975","2,882","2,951","3,000","2,853","2,700","3,396","4,398","4,131","5,308"],"Total Assets":["14,929","14,717","14,487","14,369","14,155","13,733","13,137","10,461","10,912","11,523","11,132","12,707"]}},"cash_flow":{"headers":["Mar 2015","Mar 2016","Mar 2017","Mar 2018","Mar 2019","Mar 2020","Mar 2021","Mar 2022","Mar 2023","Mar 2024","Mar 2025","Mar 2026"],"rows":{"Cash from Operating Activity":["2,100","1,490","683","228","668","945","1,341","1,441","1,466","995","850","1,341"],"Cash from Investing Activity":["-253","-11","-86","-471","-72","324","-207","-730","-502","-574","-318","-857"],"Cash from Financing Activity":["-1,609","-1,095","-522","-87","-743","-1,120","-1,154","-653","-930","103","-1,235","-518"],"Net Cash Flow":["237","384","74","-329","-146","149","-21","59","34","524","-703","-34"],"Free Cash Flow":["1,508","976","508","-241","471","959","1,144","950","990","548","558","-156"],"CFO/OP":["264%","116%","96%","47%","103%","92%","118%","98%","97%","69%","48%","56%"]}},"ratios":{"headers":["Mar 2015","Mar 2016","Mar 2017","Mar 2018","Mar 2019","Mar 2020","Mar 2021","Mar 2022","Mar 2023","Mar 2024","Mar 2025","Mar 2026"],"rows":{"Debtor Days":["69","61","70","70","56","50","62","47","64","102","78","75"],"Inventory Days":["","","","","","","","","","","",""],"Days Payable":["","","","","","","","","","","",""],"Cash Conversion Cycle":["69","61","70","70","56","50","62","47","64","102","78","75"],"Working Capital Days":["-136","-143","-290","-236","-264","-255","-115","-66","-41","-42","78","146"],"ROCE %":["2%","7%","3%","1%","1%","5%","6%","10%","10%","7%","10%","15%"]}},"shareholding":{"headers":["Jun 2023","Sep 2023","Dec 2023","Mar 2024","Jun 2024","Sep 2024","Dec 2024","Mar 2025","Jun 2025","Sep 2025","Dec 2025","Mar 2026"],"rows":{"Promoters":["63.75%","63.75%","63.75%","63.75%","63.75%","63.75%","63.75%","63.75%","63.75%","63.75%","63.75%","63.75%"],"FIIs":["2.89%","3.23%","3.27%","4.66%","4.56%","5.61%","4.79%","4.68%","6.14%","6.49%","7.13%","8.98%"],"DIIs":["7.01%","6.97%","7.99%","7.87%","8.69%","3.64%","3.63%","3.16%","2.57%","2.58%","2.41%","2.49%"],"Public":["26.36%","26.05%","24.98%","23.74%","23.01%","27.00%","27.83%","28.41%","27.55%","27.19%","26.72%","24.79%"],"No. of Shareholders":["1,83,339","2,09,199","2,19,463","3,04,527","3,24,156","4,41,535","4,52,481","4,60,808","4,63,965","4,47,555","4,19,705","3,96,720"]}},"insights":{"yearly":{"periods":["Mar 2014","Mar 2015","Mar 2016","Mar 2017","Mar 2018","Mar 2019","Mar 2020","Mar 2021","Mar 2022","Mar 2023","Mar 2024","Mar 2025"],"rows":[{"metric":"Fleet Size (Owned Vessels)","unit":"Number","values":{"Mar 2025":"xxxxxxxxxxxxxxxxxxxxxxxxx.xxx.xxx.xxx.xxx.xxx.xxx.xxx.xxx.xxx.xxx.xxx.xxxxxxxxxxxxxxxxxxxxxxxxxx.xxx.xxx.xxxx.xxxx.xxxx.xxxx.xxxx.xxUnlock insightsFree users can unlock up to 5 insights tables per month.Unlock"}}]}},"pros":["Company has been maintaining a healthy dividend payout of 19.1%"],"cons":["The company has delivered a poor sales growth of 9.31% over past five years.","Tax rate seems low","Company has a low return on equity of 12.2% over last 3 years.","Contingent liabilities of Rs.4,305 Cr.","Company might be capitalizing the interest cost","Working capital days have increased from 60.4 days to 146 days"],"analysis":{"trends":{"yearly":{"Sales":{"label":"Inconsistent","n":3,"unit":"yrs"},"Net Profit":{"label":"Inconsistent","n":3,"unit":"yrs"},"OPM%":{"label":"Increasing","n":4,"unit":"yrs"},"EPS":{"label":"Inconsistent","n":3,"unit":"yrs"},"Reserves":{"label":"Increasing","n":5,"unit":"yrs"},"Net Cash Flow":{"label":"Inconsistent","n":2,"unit":"yrs"},"Operating Cash Flow":{"label":"Inconsistent","n":2,"unit":"yrs"},"ROCE":{"label":"Inconsistent","n":3,"unit":"yrs"}},"quarterly":{"Sales":{"label":"Inconsistent","n":2,"unit":"qtrs"},"Net Profit":{"label":"Inconsistent","n":3,"unit":"qtrs"},"OPM%":{"label":"Inconsistent","n":2,"unit":"qtrs"},"EPS":{"label":"Inconsistent","n":3,"unit":"qtrs"},"Promoter Holding":{"label":"Inconsistent","n":1,"unit":"qtrs"},"Institutional Holding":{"label":"Increasing","n":5,"unit":"qtrs"}}},"cyclical":{"label":"CYCLICAL","positive_quarters":["Mar","Dec"],"negative_quarters":["Jun","Sep"]},"growth_insight":{"label":"PRICE-LED","long":"Price grew 28% vs profit 17% (5Y) \u2014 stock ahead of fundamentals; watch valuation.","recent":"Recently, profit growth exceeds 1-year price growth by 34% (ratio 2.10), the company is starting to outperform expectations."},"money_flow":{"label":"POSITIVE MONEY FLOW","change":1.93,"note":"Tracks institutional (FII+DII) holding change \u2014 proxy for smart-money flow."},"dcf":{"ok":true,"inputs":{"earnings":1326,"growth":17.0,"discount":10,"terminal_growth":2,"years":10,"terminal_multiple":12.8},"dcf":{"rows":[{"year":1,"earnings":1551,"growth":17.0,"pv":1410},{"year":2,"earnings":1815,"growth":17.0,"pv":1500},{"year":3,"earnings":2124,"growth":17.0,"pv":1596},{"year":4,"earnings":2485,"growth":17.0,"pv":1697},{"year":5,"earnings":2907,"growth":17.0,"pv":1805},{"year":6,"earnings":3401,"growth":17.0,"pv":1920},{"year":7,"earnings":3980,"growth":17.0,"pv":2042},{"year":8,"earnings":4656,"growth":17.0,"pv":2172},{"year":9,"earnings":5448,"growth":17.0,"pv":2310},{"year":10,"earnings":6374,"growth":17.0,"pv":2457}],"pv_1_n":18910,"terminal_year_cf":6501,"terminal_value":81267,"pv_terminal":31332,"effective_multiple":12.8,"total_pv":50242},"reverse":{"rows":[{"year":1,"earnings":1315,"growth":-0.83,"pv":1195},{"year":2,"earnings":1304,"growth":-0.83,"pv":1078},{"year":3,"earnings":1293,"growth":-0.83,"pv":972},{"year":4,"earnings":1283,"growth":-0.83,"pv":876},{"year":5,"earnings":1272,"growth":-0.83,"pv":790},{"year":6,"earnings":1261,"growth":-0.83,"pv":712},{"year":7,"earnings":1251,"growth":-0.83,"pv":642},{"year":8,"earnings":1240,"growth":-0.83,"pv":579},{"year":9,"earnings":1230,"growth":-0.83,"pv":522},{"year":10,"earnings":1220,"growth":-0.83,"pv":470}],"pv_1_n":7835,"terminal_year_cf":1244,"terminal_value":15555,"pv_terminal":5997,"effective_multiple":12.8,"total_pv":13832,"implied_growth":-0.83},"intrinsic_total":50242,"intrinsic_per_share":1078,"current_price":297.0,"market_cap":13837.0,"margin_of_safety":72.5}}},"prices":{"ok":true,"ticker":"SCI.NS","yearwise":[{"year":2002,"ret":-28.46},{"year":2003,"ret":222.11},{"year":2004,"ret":-2.75},{"year":2005,"ret":-3.38},{"year":2006,"ret":5.13},{"year":2007,"ret":108.15},{"year":2008,"ret":-61.16},{"year":2009,"ret":94.09},{"year":2010,"ret":-8.88},{"year":2011,"ret":-61.01},{"year":2012,"ret":12.36},{"year":2013,"ret":-21.44},{"year":2014,"ret":37.53},{"year":2015,"ret":59.71},{"year":2016,"ret":-37.33},{"year":2017,"ret":61.71},{"year":2018,"ret":-49.1},{"year":2019,"ret":28.76},{"year":2020,"ret":44.4},{"year":2021,"ret":53.12},{"year":2022,"ret":1.02},{"year":2023,"ret":20.23},{"year":2024,"ret":28.49},{"year":2025,"ret":15.68},{"year":2026,"ret":29.86}],"heatmap":{"months":["Jan","Feb","Mar","Apr","May","Jun","Jul","Aug","Sep","Oct","Nov","Dec"],"rows":[{"year":2002,"vals":[null,null,null,null,null,null,null,1.48,-7.28,-12.36,-9.82,16.68],"annual":-13.23},{"year":2003,"vals":[-7.85,-3.54,-10.94,32.51,17.08,-4.59,-8.68,45.18,8.11,26.64,40.14,8.06],"annual":222.1},{"year":2004,"vals":[-16.25,-4.19,-12.37,-6.92,-26.73,17.69,22.38,-5.04,21.07,18.66,8.23,-4.64],"annual":-2.75},{"year":2005,"vals":[-4.37,-1.07,-8.06,-4.75,5.3,-5.44,3.25,7.38,1.06,-3.01,3.21,4.42],"annual":-3.38},{"year":2006,"vals":[0.95,-3.65,12.84,-7.67,-12.42,-0.15,-7.27,15.04,9.51,3.41,0.15,-1.96],"annual":5.11},{"year":2007,"vals":[9.48,-4.89,2.9,28.55,-2.0,-6.43,7.13,-8.42,15.86,8.62,10.86,20.42],"annual":108.18},{"year":2008,"vals":[-37.14,8.78,-7.73,22.38,15.59,-22.97,6.28,-9.93,-28.26,-13.19,-16.19,13.07],"annual":-61.16},{"year":2009,"vals":[8.92,-13.78,2.88,6.63,66.83,-9.1,8.04,4.32,5.46,-8.03,9.92,3.39],"annual":94.09},{"year":2010,"vals":[6.56,-9.49,9.26,5.94,-2.76,-1.65,2.44,-0.43,3.65,6.92,-17.01,-9.01],"annual":-8.87},{"year":2011,"vals":[-12.59,-10.53,8.04,3.58,-6.24,-1.87,-0.88,-15.42,-0.4,-11.02,-18.0,-20.54],"annual":-61.02},{"year":2012,"vals":[36.24,6.71,-11.36,-0.64,-16.87,11.22,-3.86,-6.84,16.26,-14.66,5.13,1.6],"annual":12.36},{"year":2013,"vals":[-0.65,-12.84,-14.09,6.46,-14.35,-6.4,-14.26,4.07,22.35,-7.87,4.05,18.22],"annual":-21.45},{"year":2014,"vals":[-13.41,-3.94,17.4,2.89,40.16,15.54,-16.12,3.71,-5.4,5.89,3.15,-5.95],"annual":37.55},{"year":2015,"vals":[-3.76,5.16,-21.47,1.18,10.74,-3.75,29.04,4.95,11.27,4.77,4.87,12.54],"annual":59.71},{"year":2016,"vals":[-12.21,-32.4,17.24,7.7,-1.36,-3.12,7.93,-8.11,2.41,-0.07,-13.34,-0.51],"annual":-37.34},{"year":2017,"vals":[14.1,-6.07,22.25,5.22,-7.94,15.49,-3.44,20.71,-10.36,3.01,1.08,1.39],"annual":61.67},{"year":2018,"vals":[-14.32,-11.6,-10.47,16.21,-13.62,-8.07,7.18,-14.34,-23.28,5.4,-3.98,14.1],"annual":-49.1},{"year":2019,"vals":[-15.37,-14.23,7.44,-8.39,-4.94,-4.28,-8.31,-2.44,54.46,33.53,4.76,2.48],"annual":28.76},{"year":2020,"vals":[-3.31,-24.94,-16.67,16.8,7.65,21.1,-5.43,8.8,-9.62,-2.39,9.48,57.77],"annual":44.38},{"year":2021,"vals":[-3.51,17.3,10.7,-5.65,9.29,-3.02,-0.27,-3.93,14.6,5.69,15.96,-9.19],"annual":53.11},{"year":2022,"vals":[-9.15,-15.21,10.97,15.78,-11.46,-17.42,6.71,13.48,-3.45,14.19,4.04,0.52],"annual":1.04},{"year":2023,"vals":[-2.28,-9.94,-21.77,-2.56,4.0,6.27,2.98,25.53,12.43,-4.62,3.2,13.36],"annual":20.24},{"year":2024,"vals":[29.96,11.76,-11.75,8.84,8.12,2.5,13.84,-6.1,-2.81,-17.14,8.54,-11.05],"annual":28.5},{"year":2025,"vals":[-6.44,-25.34,13.25,7.7,13.21,11.06,-3.53,-2.05,8.51,16.61,-9.68,-0.02],"annual":15.66},{"year":2026,"vals":[-2.76,18.45,-16.61,38.59,-4.0,1.63,null,null,null,null,null,null],"annual":29.87}]},"risk":{"avg_weekly":0.39,"weekly_std":6.61,"ann_vol":47.68,"max_drawdown":-86.03,"pct_positive":49.16,"sharpe":0.42,"sortino":0.72},"technical":{"ret_3m":23.75,"excess_3m":21.28,"ret_6m":32.5,"excess_6m":37.21,"ret_12m":46.65,"excess_12m":47.14,"rs_rating":100,"price":297.05,"above_50dma":false,"above_200dma":true,"golden_cross":true,"pos_52w":69.03,"dist_52w_high":-13.82,"benchmark":"Nifty 500"}},"signal":{"label":"BUY","composite":85,"confidence":"Medium","blocks":{"results":{"score":80,"reasons":["Sales +14% YoY","Net profit +141% YoY","profit growth >20% YoY","profit up QoQ","margins expanding","earnings growth decelerating"],"metrics":{"sales_yoy":14.2,"np_yoy":140.7,"np_qoq":5.3,"eps_yoy":140.0,"accel":-363.9,"opm_exp":13.0}},"technical":{"score":100,"reasons":["RS rating 100 (market-beating)","+21% vs Nifty 500 (3M)","above 200-DMA","golden cross (50>200)"],"metrics":{"rs_rating":100,"excess_3m":21.28,"excess_12m":47.14,"above_200dma":true,"golden_cross":true,"pos_52w":69.03}},"fundamental":{"score":74,"reasons":["ROE 16%","DCF margin of safety 72%","institutional inflow"],"metrics":{"roe":16.3,"roce":14.8,"dcf_mos":72.5}}},"weights":{"results":0.3,"technical":0.35,"fundamental":0.35},"reasons_pos":["Sales +14% YoY","Net profit +141% YoY","profit growth >20% YoY","profit up QoQ","margins expanding","ROE 16%"],"reasons_neg":["earnings growth decelerating"],"ticker":"SCI.NS","disclaimer":"Rules-based screen for research/education only \u2014 not personalized investment advice. Verify independently before any decision.","bias_check":{"risk":"LOW","principle":"Markets price expectations, not your conviction \u2014 weigh valuation, the macro and the data, not just the story.","flags":[{"level":"info","title":"Size it \u2014 don't fall in love","note":"Even a clean BUY deserves a position cap and an exit plan. Concentrated conviction (loyalty to one name) is how good theses become big drawdowns.","lesson":"Amazon: a great company held with no diversification became the biggest single loss."}],"source":"Insider-Bias checklist"}}}