{"ts":1783924051,"ist":"11:57 IST","date":"2026-07-13","source":"BSE real-time (direct)","quotes":{"HDFCBANK":{"ltp":818.35,"pct":-0.72,"open":816.95,"high":821.95,"low":810.8,"prev_close":824.25},"BHARTIARTL":{"ltp":1899.7,"pct":-1.11,"open":1908.15,"high":1915.45,"low":1896.3,"prev_close":1921.1},"RELIANCE":{"ltp":1297.1,"pct":-0.9,"open":1298.15,"high":1306.0,"low":1296.65,"prev_close":1308.85},"TCS":{"ltp":2178.8,"pct":5.3,"open":2069.15,"high":2179.6,"low":2062.5,"prev_close":2069.05,"vwap":2130.46,"vol":668000},"LICI":{"ltp":439.35,"pct":-0.79,"open":441.5,"high":442.85,"low":438.0,"prev_close":442.85},"BAJFINANCE":{"ltp":1017.8,"pct":-0.26,"open":1014.95,"high":1020.3,"low":1003.7,"prev_close":1020.45},"SBIN":{"ltp":1034.4,"pct":-0.17,"open":1021.5,"high":1042.35,"low":1021.5,"prev_close":1036.15},"LT":{"ltp":3930.15,"pct":-0.42,"open":3899.95,"high":3937.65,"low":3881.0,"prev_close":3946.55},"SUNPHARMA":{"ltp":1922.6,"pct":-0.65,"open":1935.0,"high":1935.0,"low":1911.55,"prev_close":1935.25},"MARUTI":{"ltp":13765.65,"pct":-0.68,"open":13660.05,"high":13844.15,"low":13540.0,"prev_close":13859.25},"TITAN":{"ltp":4603.95,"pct":0.39,"open":4574.5,"high":4607.9,"low":4522.35,"prev_close":4586.1},"ADANIPOWER":{"ltp":216.15,"pct":-1.05,"open":217.4,"high":218.7,"low":215.6,"prev_close":218.4},"ADANIPORTS":{"ltp":1811.55,"pct":-0.9,"open":1814.6,"high":1825.1,"low":1807.55,"prev_close":1828.0},"M&M":{"ltp":3144.75,"pct":0.5,"open":3096.3,"high":3156.35,"low":3084.0,"prev_close":3129.15},"AXISBANK":{"ltp":1317.25,"pct":-0.49,"open":1319.95,"high":1329.85,"low":1314.3,"prev_close":1323.75},"ITC":{"ltp":280.55,"pct":-0.48,"open":281.05,"high":281.6,"low":279.35,"prev_close":281.9},"ADANIENT":{"ltp":3175.35,"pct":0.64,"open":3130.0,"high":3187.95,"low":3114.1,"prev_close":3155.15},"NTPC":{"ltp":346.9,"pct":0.7,"open":345.45,"high":348.45,"low":344.0,"prev_close":344.5},"ULTRACEMCO":{"ltp":11578.0,"pct":-1.16,"open":11507.9,"high":11615.8,"low":11507.9,"prev_close":11713.55},"HCLTECH":{"ltp":1206.95,"pct":3.81,"open":1164.4,"high":1206.95,"low":1162.4,"prev_close":1162.65,"vwap":1186.97,"vol":292000},"ONGC":{"ltp":247.3,"pct":0.94,"open":246.25,"high":248.85,"low":245.6,"prev_close":245.0},"BAJAJ-AUTO":{"ltp":10295.95,"pct":1.3,"open":10065.0,"high":10355.0,"low":10045.1,"prev_close":10163.4},"JSWSTEEL":{"ltp":1225.2,"pct":-1.63,"open":1238.05,"high":1239.6,"low":1220.0,"prev_close":1245.55},"HAL":{"ltp":4476.25,"pct":-0.67,"open":4505.65,"high":4510.55,"low":4440.0,"prev_close":4506.55},"ETERNAL":{"ltp":285.65,"pct":-1.38,"open":285.15,"high":288.8,"low":284.45,"prev_close":289.65},"BEL":{"ltp":409.5,"pct":-1.3,"open":411.5,"high":411.9,"low":408.4,"prev_close":414.9},"HINDUNILVR":{"ltp":2126.0,"pct":-1.08,"open":2146.8,"high":2146.8,"low":2120.0,"prev_close":2149.3},"ICICIBANK":{"ltp":1398.5,"pct":-0.21,"open":1390.1,"high":1405.35,"low":1385.9,"prev_close":1401.45},"DMART":{"ltp":3977.05,"pct":-2.6,"open":3950.0,"high":4010.0,"low":3910.0,"prev_close":4083.05,"vwap":3972.62,"vol":65000},"POWERGRID":{"ltp":285.0,"pct":0.64,"open":283.2,"high":285.35,"low":281.8,"prev_close":283.2},"COALINDIA":{"ltp":426.8,"pct":-0.62,"open":428.8,"high":431.9,"low":425.0,"prev_close":429.45},"ASIANPAINT":{"ltp":2646.05,"pct":-1.19,"open":2642.4,"high":2662.35,"low":2627.8,"prev_close":2677.8},"TATASTEEL":{"ltp":185.7,"pct":-2.85,"open":189.9,"high":189.9,"low":185.5,"prev_close":191.15,"vwap":187.07,"vol":908000},"GRASIM":{"ltp":3159.1,"pct":-1.65,"open":3211.9,"high":3216.8,"low":3146.6,"prev_close":3212.05},"KOTAKBANK":{"ltp":378.95,"pct":0.3,"open":375.6,"high":379.0,"low":375.35,"prev_close":377.8},"HINDZINC":{"ltp":532.55,"pct":-0.77,"open":528.8,"high":534.45,"low":526.2,"prev_close":536.7},"INFY":{"ltp":1096.0,"pct":2.63,"open":1057.0,"high":1097.0,"low":1056.95,"prev_close":1068.05,"vwap":1077.61,"vol":508000},"EICHERMOT":{"ltp":7271.85,"pct":-1.25,"open":7348.25,"high":7348.25,"low":7265.0,"prev_close":7364.2},"ADANIENSOL":{"ltp":1647.0,"pct":-0.43,"open":1647.05,"high":1667.7,"low":1635.3,"prev_close":1654.15},"HINDALCO":{"ltp":958.85,"pct":-0.85,"open":964.05,"high":965.4,"low":955.95,"prev_close":967.1},"BAJAJFINSV":{"ltp":1890.0,"pct":-1.33,"open":1905.85,"high":1905.85,"low":1884.3,"prev_close":1915.55},"IOC":{"ltp":138.1,"pct":-0.61,"open":137.7,"high":138.7,"low":136.6,"prev_close":138.95},"VAML":{"ltp":451.5,"pct":1.84,"open":442.8,"high":452.85,"low":440.85,"prev_close":443.35},"WIPRO":{"ltp":177.75,"pct":1.37,"open":174.8,"high":177.75,"low":174.4,"prev_close":175.35},"NESTLEIND":{"ltp":1438.3,"pct":-1.26,"open":1454.9,"high":1454.9,"low":1429.9,"prev_close":1456.65},"DLF":{"ltp":674.9,"pct":-1.58,"open":683.15,"high":690.1,"low":673.6,"prev_close":685.7},"SOLARINDS":{"ltp":18136.2,"pct":-0.55,"open":18052.15,"high":18250.0,"low":17963.4,"prev_close":18236.8},"HYUNDAI":{"ltp":1983.4,"pct":0.02,"open":1962.3,"high":1988.0,"low":1943.85,"prev_close":1983.0},"PIDILITIND":{"ltp":1572.65,"pct":-1.6,"open":1575.75,"high":1578.15,"low":1559.4,"prev_close":1598.15},"JIOFIN":{"ltp":241.05,"pct":-0.33,"open":239.8,"high":243.5,"low":239.0,"prev_close":241.85},"TVSMOTOR":{"ltp":3671.65,"pct":1.37,"open":3620.35,"high":3695.05,"low":3572.65,"prev_close":3621.85},"ADANIGREEN":{"ltp":1552.75,"pct":1.07,"open":1524.95,"high":1575.05,"low":1522.4,"prev_close":1536.3},"SHRIRAMFIN":{"ltp":1042.1,"pct":-0.22,"open":1022.1,"high":1047.25,"low":1020.55,"prev_close":1044.4},"VBL":{"ltp":468.15,"pct":-2.09,"open":477.95,"high":478.15,"low":465.4,"prev_close":478.15},"TRENT":{"ltp":2896.7,"pct":-0.21,"open":2893.0,"high":2911.0,"low":2863.8,"prev_close":2902.75},"INDIGO":{"ltp":5208.0,"pct":-1.94,"open":5207.8,"high":5239.55,"low":5138.55,"prev_close":5311.05},"TATACAP":{"ltp":359.9,"pct":-0.15,"open":357.25,"high":361.4,"low":354.05,"prev_close":360.45},"CHOLAFIN":{"ltp":1811.1,"pct":0.14,"open":1800.0,"high":1818.9,"low":1777.0,"prev_close":1808.55},"IDEA":{"ltp":13.97,"pct":-1.62,"open":14.14,"high":14.16,"low":13.94,"prev_close":14.2},"MOTHERSON":{"ltp":142.25,"pct":-0.66,"open":141.95,"high":143.2,"low":141.05,"prev_close":143.2},"SBILIFE":{"ltp":1850.05,"pct":-0.7,"open":1850.0,"high":1855.75,"low":1832.1,"prev_close":1863.15},"ABB":{"ltp":6780.0,"pct":-0.78,"open":6819.65,"high":6874.45,"low":6725.0,"prev_close":6833.55},"DIVISLAB":{"ltp":6804.5,"pct":-0.46,"open":6832.35,"high":6844.55,"low":6791.0,"prev_close":6835.7},"BHEL":{"ltp":409.4,"pct":3.57,"open":392.3,"high":411.8,"low":390.0,"prev_close":395.3,"vwap":406.58,"vol":1452000},"POWERINDIA":{"ltp":31907.9,"pct":-2.13,"open":32025.1,"high":32269.3,"low":31800.0,"prev_close":32602.95},"TORNTPHARM":{"ltp":4915.65,"pct":0.25,"open":4905.0,"high":4974.05,"low":4871.2,"prev_close":4903.35},"PFC":{"ltp":401.55,"pct":-1.22,"open":403.0,"high":404.5,"low":399.9,"prev_close":406.5},"GROWW":{"ltp":206.75,"pct":1.05,"open":202.0,"high":207.4,"low":200.95,"prev_close":204.6},"BRITANNIA":{"ltp":5363.8,"pct":0.19,"open":5353.35,"high":5363.8,"low":5300.0,"prev_close":5353.7},"UNIONBANK":{"ltp":166.4,"pct":1.16,"open":163.35,"high":169.15,"low":162.95,"prev_close":164.5},"APOLLOHOSP":{"ltp":8835.0,"pct":-0.07,"open":8850.0,"high":8920.6,"low":8776.15,"prev_close":8841.55},"TMCV":{"ltp":418.25,"pct":-1.02,"open":416.8,"high":420.8,"low":415.55,"prev_close":422.55},"TMPV":{"ltp":337.3,"pct":-0.24,"open":337.05,"high":339.6,"low":334.4,"prev_close":338.1},"CUMMINSIND":{"ltp":5570.95,"pct":-0.87,"open":5600.0,"high":5600.0,"low":5536.8,"prev_close":5619.6},"ICICIAMC":{"ltp":3180.0,"pct":0.63,"open":3160.15,"high":3181.0,"low":3137.6,"prev_close":3160.1},"TECHM":{"ltp":1501.0,"pct":3.13,"open":1428.4,"high":1501.25,"low":1428.4,"prev_close":1455.45,"vwap":1475.38,"vol":87000},"MUTHOOTFIN":{"ltp":3072.85,"pct":-1.81,"open":3070.2,"high":3110.7,"low":3048.0,"prev_close":3129.65},"CGPOWER":{"ltp":904.8,"pct":-1.29,"open":908.4,"high":914.3,"low":902.05,"prev_close":916.6},"BOSCHLTD":{"ltp":41820.1,"pct":0.03,"open":42108.35,"high":42108.35,"low":41362.75,"prev_close":41807.65},"ENRIN":{"ltp":3455.45,"pct":-1.75,"open":3499.8,"high":3520.0,"low":3424.25,"prev_close":3516.95},"BPCL":{"ltp":304.6,"pct":-1.65,"open":303.75,"high":307.0,"low":302.2,"prev_close":309.7},"LTM":{"ltp":4125.5,"pct":2.09,"open":4041.35,"high":4129.05,"low":3975.2,"prev_close":4041.15},"PNB":{"ltp":105.15,"pct":-0.24,"open":104.95,"high":105.95,"low":104.0,"prev_close":105.4},"POLYCAB":{"ltp":9301.0,"pct":1.01,"open":9246.15,"high":9426.45,"low":9150.55,"prev_close":9208.45},"BAJAJHLDNG":{"ltp":10804.25,"pct":1.33,"open":10515.75,"high":10909.5,"low":10218.25,"prev_close":10662.75},"IRFC":{"ltp":89.17,"pct":-0.79,"open":90.09,"high":90.09,"low":88.75,"prev_close":89.88},"GVT&D":{"ltp":4536.55,"pct":-2.98,"open":4658.8,"high":4658.8,"low":4522.15,"prev_close":4675.8,"vwap":4580.37,"vol":985300000},"BANKBARODA":{"ltp":249.75,"pct":-0.5,"open":249.45,"high":252.1,"low":247.3,"prev_close":251.0},"CANBK":{"ltp":127.55,"pct":-0.97,"open":127.35,"high":128.8,"low":126.3,"prev_close":128.8},"HDFCAMC":{"ltp":2684.5,"pct":-2.81,"open":2750.0,"high":2750.0,"low":2681.85,"prev_close":2762.1,"vwap":2702.94,"vol":18000},"LUPIN":{"ltp":2497.15,"pct":0.04,"open":2504.95,"high":2509.1,"low":2485.75,"prev_close":2496.05},"INDIANB":{"ltp":846.15,"pct":-2.85,"open":869.5,"high":871.0,"low":845.25,"prev_close":870.95,"vwap":860.28,"vol":169000},"HDFCLIFE":{"ltp":571.35,"pct":0.8,"open":564.3,"high":577.05,"low":562.85,"prev_close":566.8},"GAIL":{"ltp":170.65,"pct":-1.7,"open":171.5,"high":173.5,"low":170.55,"prev_close":173.6},"SIEMENS":{"ltp":3470.4,"pct":-0.93,"open":3498.25,"high":3498.25,"low":3446.0,"prev_close":3503.15},"MARICO":{"ltp":845.6,"pct":-0.81,"open":853.6,"high":853.6,"low":843.25,"prev_close":852.5},"GODREJCP":{"ltp":1073.95,"pct":-1.35,"open":1083.5,"high":1083.5,"low":1070.0,"prev_close":1088.65},"MAXHEALTH":{"ltp":1109.2,"pct":0.09,"open":1110.0,"high":1110.0,"low":1093.8,"prev_close":1108.15},"ZYDUSLIFE":{"ltp":1133.5,"pct":-1.48,"open":1147.1,"high":1154.85,"low":1133.0,"prev_close":1150.5},"GMRAIRPORT":{"ltp":113.6,"pct":0.98,"open":112.45,"high":114.25,"low":111.75,"prev_close":112.5},"LODHA":{"ltp":1189.25,"pct":-2.61,"open":1206.05,"high":1219.75,"low":1185.0,"prev_close":1221.15,"vwap":1200.67,"vol":143000},"AMBUJACEM":{"ltp":431.2,"pct":-1.16,"open":430.9,"high":433.8,"low":429.5,"prev_close":436.25},"CIPLA":{"ltp":1428.1,"pct":-0.74,"open":1438.75,"high":1442.45,"low":1421.0,"prev_close":1438.75},"VEDL":{"ltp":269.15,"pct":-1.27,"open":270.7,"high":271.25,"low":268.7,"prev_close":272.6},"TATAPOWER":{"ltp":376.1,"pct":-1.35,"open":380.7,"high":380.7,"low":376.0,"prev_close":381.25},"MANKIND":{"ltp":2514.65,"pct":-0.4,"open":2527.55,"high":2527.55,"low":2496.1,"prev_close":2524.85},"DRREDDY":{"ltp":1231.6,"pct":-1.12,"open":1241.1,"high":1249.1,"low":1227.65,"prev_close":1245.5},"BHARATFORG":{"ltp":2131.1,"pct":0.71,"open":2114.25,"high":2143.0,"low":2100.0,"prev_close":2116.1},"LLOYDSME":{"ltp":1818.4,"pct":1.1,"open":1798.0,"high":1833.0,"low":1779.45,"prev_close":1798.55},"ABCAPITAL":{"ltp":404.1,"pct":-1.02,"open":404.95,"high":407.0,"low":400.0,"prev_close":408.25},"JSWENERGY":{"ltp":550.3,"pct":-0.54,"open":556.65,"high":556.65,"low":547.8,"prev_close":553.3},"HEROMOTOCO":{"ltp":4916.55,"pct":-0.64,"open":4893.7,"high":4950.0,"low":4875.0,"prev_close":4948.35},"TATACONSUM":{"ltp":1097.4,"pct":-1.3,"open":1105.7,"high":1105.7,"low":1096.25,"prev_close":1111.9},"INDUSTOWER":{"ltp":408.25,"pct":0.55,"open":403.0,"high":409.0,"low":401.9,"prev_close":406.0},"MAZDOCK":{"ltp":2391.6,"pct":-1.18,"open":2408.2,"high":2412.0,"low":2385.0,"prev_close":2420.1},"INDHOTEL":{"ltp":746.2,"pct":-0.78,"open":750.3,"high":750.9,"low":737.9,"prev_close":752.1},"ASHOKLEY":{"ltp":157.5,"pct":-0.03,"open":154.5,"high":158.7,"low":153.15,"prev_close":157.55},"UNITDSPR":{"ltp":1382.15,"pct":-0.31,"open":1379.95,"high":1398.9,"low":1371.05,"prev_close":1386.4},"RECLTD":{"ltp":349.0,"pct":-0.82,"open":349.6,"high":350.05,"low":347.6,"prev_close":351.9},"LGEINDIA":{"ltp":1552.8,"pct":-0.8,"open":1558.05,"high":1568.0,"low":1546.0,"prev_close":1565.3},"MEESHO":{"ltp":192.1,"pct":-1.0,"open":193.4,"high":194.0,"low":190.65,"prev_close":194.05},"AUROPHARMA":{"ltp":1551.9,"pct":-0.81,"open":1551.75,"high":1583.8,"low":1541.6,"prev_close":1564.65},"JINDALSTEL":{"ltp":1021.9,"pct":-2.82,"open":1038.8,"high":1040.2,"low":1018.0,"prev_close":1051.6,"vwap":1030.04,"vol":265000},"ICICIGI":{"ltp":1771.6,"pct":-2.96,"open":1857.9,"high":1857.9,"low":1747.15,"prev_close":1825.6,"vwap":1766.26,"vol":63000},"OFSS":{"ltp":11833.85,"pct":1.53,"open":11550.1,"high":11945.65,"low":11550.1,"prev_close":11655.95},"IDBI":{"ltp":84.05,"pct":1.39,"open":82.18,"high":84.65,"low":81.82,"prev_close":82.9},"LAURUSLABS":{"ltp":1542.3,"pct":0.26,"open":1530.55,"high":1551.7,"low":1525.6,"prev_close":1538.25},"HINDPETRO":{"ltp":389.45,"pct":-1.49,"open":386.8,"high":391.7,"low":385.6,"prev_close":395.35},"FEDERALBNK":{"ltp":336.0,"pct":1.83,"open":328.3,"high":336.5,"low":326.9,"prev_close":329.95},"DIXON":{"ltp":13464.85,"pct":0.33,"open":13417.9,"high":13532.45,"low":13200.0,"prev_close":13420.6},"LTF":{"ltp":326.6,"pct":1.67,"open":321.25,"high":333.5,"low":318.0,"prev_close":321.25},"JSWINFRA":{"ltp":351.0,"pct":6.3,"open":330.7,"high":353.9,"low":330.7,"prev_close":330.2,"vwap":345.32,"vol":861000},"PERSISTENT":{"ltp":5083.65,"pct":0.58,"open":4956.65,"high":5119.0,"low":4956.65,"prev_close":5054.2},"SHREECEM":{"ltp":26465.0,"pct":-0.41,"open":26598.95,"high":26598.95,"low":26378.8,"prev_close":26575.15},"NYKAA":{"ltp":331.4,"pct":0.41,"open":329.4,"high":332.35,"low":326.1,"prev_close":330.0},"LENSKART":{"ltp":542.45,"pct":-0.16,"open":543.0,"high":545.3,"low":535.8,"prev_close":543.3},"NHPC":{"ltp":79.16,"pct":-0.86,"open":79.02,"high":79.75,"low":78.66,"prev_close":79.85},"NTPCGREEN":{"ltp":94.38,"pct":0.31,"open":93.96,"high":95.05,"low":92.98,"prev_close":94.09},"ATGL":{"ltp":723.35,"pct":-0.1,"open":720.0,"high":735.0,"low":713.15,"prev_close":724.05},"INDUSINDBK":{"ltp":1004.35,"pct":-1.17,"open":1010.0,"high":1013.35,"low":1000.4,"prev_close":1016.25},"NAM-INDIA":{"ltp":1213.5,"pct":0.07,"open":1201.1,"high":1221.35,"low":1198.8,"prev_close":1212.65},"PAYTM":{"ltp":1351.0,"pct":0.66,"open":1320.75,"high":1360.2,"low":1320.75,"prev_close":1342.15},"WAAREEENER":{"ltp":2895.15,"pct":-0.92,"open":2909.75,"high":2911.95,"low":2882.0,"prev_close":2922.1},"HAVELLS":{"ltp":1181.9,"pct":-0.53,"open":1184.9,"high":1184.9,"low":1167.25,"prev_close":1188.25},"ICICIPRULI":{"ltp":522.85,"pct":2.46,"open":511.85,"high":527.0,"low":506.25,"prev_close":510.3},"SWIGGY":{"ltp":269.4,"pct":-1.35,"open":271.15,"high":272.65,"low":266.0,"prev_close":273.1},"YESBANK":{"ltp":23.59,"pct":-1.46,"open":23.8,"high":23.8,"low":23.59,"prev_close":23.94},"BAJAJHFL":{"ltp":88.61,"pct":0.64,"open":87.0,"high":89.49,"low":86.81,"prev_close":88.05},"SRF":{"ltp":2742.0,"pct":-1.18,"open":2773.3,"high":2775.5,"low":2742.0,"prev_close":2774.85},"SUZLON":{"ltp":53.0,"pct":-1.71,"open":53.64,"high":53.64,"low":52.9,"prev_close":53.92},"TORNTPOWER":{"ltp":1438.45,"pct":1.37,"open":1405.65,"high":1453.35,"low":1405.65,"prev_close":1419.0},"AUBANK":{"ltp":1054.25,"pct":-1.69,"open":1063.25,"high":1064.8,"low":1053.0,"prev_close":1072.35},"DABUR":{"ltp":441.7,"pct":-0.39,"open":443.45,"high":443.45,"low":439.0,"prev_close":443.45},"NAUKRI":{"ltp":1194.8,"pct":-0.77,"open":1187.75,"high":1206.7,"low":1180.55,"prev_close":1204.1},"IDFCFIRSTB":{"ltp":80.17,"pct":-0.79,"open":79.72,"high":80.59,"low":79.72,"prev_close":80.81},"OIL":{"ltp":425.4,"pct":0.09,"open":428.05,"high":431.95,"low":422.5,"prev_close":425.0},"BHARTIHEXA":{"ltp":1591.15,"pct":-0.94,"open":1583.5,"high":1610.7,"low":1578.25,"prev_close":1606.25},"COFORGE":{"ltp":1520.0,"pct":1.1,"open":1499.85,"high":1522.2,"low":1469.8,"prev_close":1503.5},"NMDC":{"ltp":83.53,"pct":-1.59,"open":84.35,"high":84.35,"low":83.3,"prev_close":84.88},"POLICYBZR":{"ltp":1587.9,"pct":0.52,"open":1570.05,"high":1593.9,"low":1567.05,"prev_close":1580.55},"ALKEM":{"ltp":5610.45,"pct":-1.05,"open":5605.7,"high":5675.0,"low":5595.8,"prev_close":5669.7},"BIOCON":{"ltp":406.0,"pct":-2.98,"open":415.25,"high":415.4,"low":405.45,"prev_close":418.45,"vwap":410.76,"vol":252000},"FORTIS":{"ltp":956.35,"pct":-1.21,"open":956.7,"high":969.4,"low":954.6,"prev_close":968.05},"BANKINDIA":{"ltp":143.15,"pct":-1.17,"open":143.9,"high":145.95,"low":142.5,"prev_close":144.85},"PHOENIXLTD":{"ltp":2142.8,"pct":0.15,"open":2153.3,"high":2155.45,"low":2114.5,"prev_close":2138.05},"MCX":{"ltp":2769.9,"pct":-0.06,"open":2751.3,"high":2815.1,"low":2751.3,"prev_close":2771.6},"SCHAEFFLER":{"ltp":4164.9,"pct":1.9,"open":4087.05,"high":4173.45,"low":4054.9,"prev_close":4087.05},"OBEROIRLTY":{"ltp":1884.0,"pct":-2.12,"open":1891.65,"high":1915.6,"low":1883.25,"prev_close":1924.9},"SAIL":{"ltp":164.8,"pct":-1.93,"open":166.0,"high":166.6,"low":164.1,"prev_close":168.05},"GODREJPROP":{"ltp":2115.5,"pct":-0.85,"open":2123.55,"high":2164.8,"low":2111.2,"prev_close":2133.6},"GICRE":{"ltp":362.85,"pct":-0.58,"open":364.5,"high":365.7,"low":362.0,"prev_close":364.95},"PRESTIGE":{"ltp":1689.0,"pct":-2.5,"open":1724.25,"high":1724.25,"low":1689.0,"prev_close":1732.35,"vwap":1700.37,"vol":158000},"HDBFS":{"ltp":749.45,"pct":-0.77,"open":746.25,"high":754.0,"low":743.0,"prev_close":755.3},"LINDEINDIA":{"ltp":7105.75,"pct":0.88,"open":7000.75,"high":7229.2,"low":6956.95,"prev_close":7043.5},"UNOMINDA":{"ltp":1165.75,"pct":0.06,"open":1154.9,"high":1168.8,"low":1146.1,"prev_close":1165.05},"BERGEPAINT":{"ltp":493.15,"pct":-0.79,"open":494.25,"high":494.5,"low":488.7,"prev_close":497.1},"ABBOTINDIA":{"ltp":27333.0,"pct":0.77,"open":27299.7,"high":27511.25,"low":27193.0,"prev_close":27124.95},"MOTILALOFS":{"ltp":968.2,"pct":-1.09,"open":967.05,"high":978.4,"low":964.0,"prev_close":978.85},"IOB":{"ltp":34.33,"pct":-0.72,"open":34.45,"high":34.92,"low":34.21,"prev_close":34.58},"GLENMARK":{"ltp":2279.3,"pct":-0.13,"open":2291.4,"high":2311.1,"low":2267.0,"prev_close":2282.25},"APARINDS":{"ltp":13973.7,"pct":-0.8,"open":13950.3,"high":14093.05,"low":13840.05,"prev_close":14086.8},"NATIONALUM":{"ltp":352.9,"pct":-0.55,"open":355.0,"high":357.1,"low":350.95,"prev_close":354.85},"MFSL":{"ltp":1647.65,"pct":0.95,"open":1642.2,"high":1660.9,"low":1620.95,"prev_close":1632.2},"THERMAX":{"ltp":4684.7,"pct":-2.51,"open":4746.3,"high":4787.0,"low":4673.3,"prev_close":4805.2,"vwap":4730.26,"vol":325000000},"MAHABANK":{"ltp":82.14,"pct":-2.5,"open":83.91,"high":84.68,"low":81.9,"prev_close":84.35,"vwap":82.99,"vol":1286000},"VMM":{"ltp":117.65,"pct":-1.09,"open":117.0,"high":118.45,"low":117.0,"prev_close":118.95},"RADICO":{"ltp":4048.85,"pct":-0.58,"open":4072.0,"high":4093.4,"low":4040.0,"prev_close":4072.3},"COROMANDEL":{"ltp":2033.15,"pct":-1.65,"open":2052.7,"high":2059.0,"low":2024.5,"prev_close":2067.35},"TATACOMM":{"ltp":1858.6,"pct":0.14,"open":1856.2,"high":1894.8,"low":1850.0,"prev_close":1856.05},"SBICARD":{"ltp":614.55,"pct":0.47,"open":608.05,"high":619.0,"low":602.55,"prev_close":611.65},"JSL":{"ltp":708.45,"pct":-1.04,"open":715.45,"high":716.15,"low":704.15,"prev_close":715.9},"SUNDARMFIN":{"ltp":4528.0,"pct":-0.99,"open":4565.0,"high":4565.0,"low":4527.0,"prev_close":4573.2},"PIRAMALFIN":{"ltp":2185.65,"pct":0.9,"open":2174.6,"high":2202.0,"low":2148.45,"prev_close":2166.1},"UPL":{"ltp":586.7,"pct":-1.34,"open":592.8,"high":592.8,"low":586.4,"prev_close":594.65},"MRF":{"ltp":132335.55,"pct":-1.53,"open":133000.0,"high":133000.0,"low":131655.4,"prev_close":134392.8},"TIINDIA":{"ltp":2914.7,"pct":-1.52,"open":2920.9,"high":2945.0,"low":2914.0,"prev_close":2959.65},"KEI":{"ltp":5133.15,"pct":-0.21,"open":5105.4,"high":5232.2,"low":5098.0,"prev_close":5144.05},"GODREJIND":{"ltp":1388.05,"pct":-2.16,"open":1373.35,"high":1402.0,"low":1366.1,"prev_close":1418.7},"HINDCOPPER":{"ltp":494.5,"pct":-0.85,"open":490.4,"high":497.05,"low":490.0,"prev_close":498.75},"FACT":{"ltp":851.85,"pct":-0.47,"open":853.25,"high":856.75,"low":847.95,"prev_close":855.85},"ATHERENERG":{"ltp":1214.4,"pct":-0.8,"open":1228.95,"high":1254.0,"low":1211.0,"prev_close":1224.25},"BDL":{"ltp":1300.75,"pct":-3.28,"open":1331.9,"high":1331.9,"low":1299.25,"prev_close":1344.85,"vwap":1312.21,"vol":94000},"COLPAL":{"ltp":2025.0,"pct":-1.31,"open":2048.3,"high":2048.3,"low":2025.0,"prev_close":2051.9},"KALYANKJIL":{"ltp":522.9,"pct":9.8,"open":472.6,"high":523.85,"low":468.7,"prev_close":476.25,"vwap":501.83,"vol":7575000},"IPCALAB":{"ltp":1832.6,"pct":2.52,"open":1786.75,"high":1840.65,"low":1764.8,"prev_close":1787.55,"vwap":1782.71,"vol":112000},"MPHASIS":{"ltp":2366.35,"pct":1.95,"open":2340.35,"high":2368.5,"low":2301.0,"prev_close":2321.0},"360ONE":{"ltp":1103.8,"pct":-2.27,"open":1101.1,"high":1121.45,"low":1095.1,"prev_close":1129.4},"AEGISLOG":{"ltp":1265.2,"pct":1.03,"open":1227.55,"high":1277.0,"low":1227.55,"prev_close":1252.35},"AIAENG":{"ltp":4680.0,"pct":0.09,"open":4730.95,"high":4740.0,"low":4651.5,"prev_close":4675.75},"VOLTAS":{"ltp":1335.0,"pct":3.78,"open":1285.2,"high":1339.7,"low":1274.5,"prev_close":1286.4,"vwap":1319.04,"vol":47000},"APLAPOLLO":{"ltp":1813.95,"pct":-1.16,"open":1835.75,"high":1835.75,"low":1810.0,"prev_close":1835.15},"PREMIERENE":{"ltp":1105.2,"pct":-1.18,"open":1111.6,"high":1114.25,"low":1098.0,"prev_close":1118.45},"AIIL":{"ltp":513.4,"pct":-0.07,"open":515.85,"high":520.0,"low":507.7,"prev_close":513.75},"WELCORP":{"ltp":1624.0,"pct":1.07,"open":1589.9,"high":1638.9,"low":1589.9,"prev_close":1606.85},"RVNL":{"ltp":229.1,"pct":-1.59,"open":229.8,"high":231.75,"low":228.5,"prev_close":232.8},"SUPREMEIND":{"ltp":3336.3,"pct":0.43,"open":3320.0,"high":3338.45,"low":3285.75,"prev_close":3322.05},"AJANTPHARM":{"ltp":3412.9,"pct":1.84,"open":3349.1,"high":3428.5,"low":3347.0,"prev_close":3351.2},"M&MFIN":{"ltp":331.75,"pct":-0.48,"open":332.0,"high":337.2,"low":330.45,"prev_close":333.35},"ANTHEM":{"ltp":750.0,"pct":-0.64,"open":748.0,"high":754.0,"low":747.15,"prev_close":754.8},"POONAWALLA":{"ltp":477.1,"pct":0.07,"open":475.8,"high":479.45,"low":469.05,"prev_close":476.75},"PAGEIND":{"ltp":40135.6,"pct":1.85,"open":39003.6,"high":40364.95,"low":39003.6,"prev_close":39406.7},"HUDCO":{"ltp":209.5,"pct":1.18,"open":208.0,"high":212.35,"low":207.2,"prev_close":207.05},"PATANJALI":{"ltp":410.0,"pct":-0.94,"open":411.5,"high":412.3,"low":408.5,"prev_close":413.9},"SONACOMS":{"ltp":668.1,"pct":0.01,"open":664.95,"high":673.0,"low":658.7,"prev_close":668.0},"BALKRISIND":{"ltp":2239.85,"pct":-0.62,"open":2211.15,"high":2250.0,"low":2198.0,"prev_close":2253.9},"FLUOROCHEM":{"ltp":3895.7,"pct":-1.12,"open":3944.25,"high":3944.25,"low":3888.05,"prev_close":3939.8},"3MINDIA":{"ltp":35690.0,"pct":0.94,"open":35369.3,"high":35690.0,"low":35220.0,"prev_close":35357.3},"GLAND":{"ltp":2428.2,"pct":-2.08,"open":2470.05,"high":2501.6,"low":2416.0,"prev_close":2479.7},"NLCINDIA":{"ltp":304.95,"pct":-3.1,"open":310.5,"high":311.55,"low":304.05,"prev_close":314.7,"vwap":308.11,"vol":50000},"IRCTC":{"ltp":499.0,"pct":-0.87,"open":500.05,"high":501.45,"low":498.0,"prev_close":503.4},"CPPLUS":{"ltp":3715.0,"pct":1.3,"open":3621.1,"high":3748.3,"low":3621.1,"prev_close":3667.15},"ASTERDM":{"ltp":813.0,"pct":0.58,"open":812.45,"high":816.05,"low":806.0,"prev_close":808.35},"PWL":{"ltp":144.3,"pct":-2.47,"open":146.45,"high":147.4,"low":143.9,"prev_close":147.95},"JBCHEPHARM":{"ltp":2432.2,"pct":-0.22,"open":2387.7,"high":2458.9,"low":2387.7,"prev_close":2437.65},"PETRONET":{"ltp":277.65,"pct":-0.54,"open":275.15,"high":278.0,"low":275.15,"prev_close":279.15},"NH":{"ltp":2029.95,"pct":0.16,"open":2033.2,"high":2033.2,"low":2012.75,"prev_close":2026.7},"JKCEMENT":{"ltp":5376.2,"pct":-0.41,"open":5397.85,"high":5440.0,"low":5299.0,"prev_close":5398.55},"PIIND":{"ltp":2578.0,"pct":-1.09,"open":2607.0,"high":2607.0,"low":2573.9,"prev_close":2606.35},"NAVINFLUOR":{"ltp":7630.0,"pct":-1.13,"open":7650.6,"high":7711.15,"low":7627.5,"prev_close":7716.85},"DELHIVERY":{"ltp":512.6,"pct":-1.47,"open":519.7,"high":519.7,"low":511.1,"prev_close":520.25},"KPRMILL":{"ltp":1113.3,"pct":0.43,"open":1102.75,"high":1130.1,"low":1090.8,"prev_close":1108.5},"GLAXO":{"ltp":2425.1,"pct":-0.43,"open":2440.0,"high":2440.0,"low":2408.75,"prev_close":2435.5},"KIRLOSENG":{"ltp":2540.0,"pct":1.92,"open":2485.0,"high":2569.2,"low":2475.75,"prev_close":2492.25},"ANANDRATHI":{"ltp":2124.45,"pct":-1.2,"open":2140.05,"high":2142.35,"low":2104.85,"prev_close":2150.35},"STARHEALTH":{"ltp":605.05,"pct":0.31,"open":602.15,"high":614.55,"low":598.75,"prev_close":603.2},"NUVAMA":{"ltp":1925.05,"pct":-2.61,"open":1947.8,"high":1981.3,"low":1918.45,"prev_close":1976.65,"vwap":1958.38,"vol":818300000},"ASTRAL":{"ltp":1321.2,"pct":-0.93,"open":1333.8,"high":1333.8,"low":1315.25,"prev_close":1333.65},"CONCOR":{"ltp":458.2,"pct":-1.3,"open":461.45,"high":463.95,"low":458.15,"prev_close":464.25},"LTTS":{"ltp":3300.8,"pct":0.7,"open":3289.25,"high":3325.0,"low":3251.35,"prev_close":3277.85},"BLUESTARCO":{"ltp":1689.05,"pct":1.67,"open":1660.45,"high":1695.05,"low":1644.75,"prev_close":1661.3},"ITCHOTELS":{"ltp":186.15,"pct":-0.53,"open":185.1,"high":187.5,"low":183.95,"prev_close":187.15},"COCHINSHIP":{"ltp":1412.5,"pct":-0.39,"open":1414.3,"high":1419.0,"low":1400.0,"prev_close":1418.0},"ENDURANCE":{"ltp":2700.05,"pct":0.52,"open":2682.75,"high":2707.9,"low":2635.0,"prev_close":2686.05},"EMCURE":{"ltp":1819.05,"pct":0.48,"open":1813.3,"high":1838.85,"low":1800.0,"prev_close":1810.45},"BANDHANBNK":{"ltp":211.45,"pct":0.57,"open":207.55,"high":212.85,"low":207.15,"prev_close":210.25},"MEDANTA":{"ltp":1335.0,"pct":-0.12,"open":1336.65,"high":1345.0,"low":1325.6,"prev_close":1336.65},"EXIDEIND":{"ltp":416.75,"pct":-1.83,"open":420.6,"high":422.4,"low":416.25,"prev_close":424.5},"SCHNEIDER":{"ltp":1409.95,"pct":-0.31,"open":1410.05,"high":1443.5,"low":1395.7,"prev_close":1414.4},"KIMS":{"ltp":810.05,"pct":-0.66,"open":814.9,"high":814.9,"low":802.1,"prev_close":815.45},"HEXT":{"ltp":574.95,"pct":4.44,"open":549.4,"high":575.0,"low":543.9,"prev_close":550.5,"vwap":563.21,"vol":57999},"UBL":{"ltp":1324.0,"pct":-0.38,"open":1331.45,"high":1340.9,"low":1319.0,"prev_close":1329.0},"ABSLAMC":{"ltp":1154.25,"pct":0.82,"open":1148.9,"high":1158.2,"low":1139.25,"prev_close":1144.9},"IREDA":{"ltp":124.35,"pct":-1.62,"open":124.1,"high":125.4,"low":123.5,"prev_close":126.4},"GODFRYPHLP":{"ltp":2091.0,"pct":-1.07,"open":2112.0,"high":2112.0,"low":2085.65,"prev_close":2113.6},"ESCORTS":{"ltp":2967.4,"pct":0.82,"open":2941.0,"high":2996.0,"low":2927.4,"prev_close":2943.2},"HFCL":{"ltp":213.2,"pct":-1.93,"open":212.9,"high":218.6,"low":211.65,"prev_close":217.4},"TATAINVEST":{"ltp":684.6,"pct":-1.26,"open":693.35,"high":693.5,"low":682.9,"prev_close":693.35},"ANGELONE":{"ltp":338.8,"pct":-2.11,"open":342.25,"high":345.0,"low":335.5,"prev_close":346.1},"AEGISVOPAK":{"ltp":282.15,"pct":-0.39,"open":280.45,"high":289.0,"low":271.85,"prev_close":283.25},"HONAUT":{"ltp":38159.95,"pct":0.0,"open":37939.9,"high":38245.0,"low":37939.9,"prev_close":38159.5},"TATATECH":{"ltp":750.5,"pct":4.45,"open":711.2,"high":753.0,"low":709.0,"prev_close":718.55,"vwap":739.49,"vol":129000},"HSCL":{"ltp":660.75,"pct":0.08,"open":658.2,"high":667.8,"low":654.3,"prev_close":660.2},"GRSE":{"ltp":2629.15,"pct":-1.23,"open":2625.3,"high":2641.9,"low":2608.75,"prev_close":2661.95},"UCOBANK":{"ltp":26.5,"pct":-0.97,"open":26.25,"high":26.85,"low":26.25,"prev_close":26.76},"NIACL":{"ltp":181.05,"pct":-1.63,"open":182.85,"high":183.25,"low":176.65,"prev_close":184.05},"CENTRALBK":{"ltp":32.49,"pct":-0.37,"open":32.0,"high":32.86,"low":32.0,"prev_close":32.61},"IKS":{"ltp":1909.0,"pct":-0.83,"open":1919.35,"high":1931.95,"low":1891.25,"prev_close":1924.9},"DALBHARAT":{"ltp":1761.4,"pct":-1.36,"open":1786.5,"high":1786.5,"low":1761.4,"prev_close":1785.6},"WOCKPHARMA":{"ltp":1804.1,"pct":-0.41,"open":1801.9,"high":1819.95,"low":1791.9,"prev_close":1811.45},"PGHH":{"ltp":8949.05,"pct":0.12,"open":9027.95,"high":9027.95,"low":8910.0,"prev_close":8938.3},"MANAPPURAM":{"ltp":333.5,"pct":-2.13,"open":335.1,"high":338.8,"low":330.2,"prev_close":340.75},"PNBHOUSING":{"ltp":1106.0,"pct":-0.4,"open":1110.6,"high":1132.0,"low":1100.0,"prev_close":1110.45},"TVSHLTD":{"ltp":14310.05,"pct":2.23,"open":14016.0,"high":14343.0,"low":13991.95,"prev_close":13997.8},"LICHSGFIN":{"ltp":552.4,"pct":0.45,"open":542.2,"high":554.7,"low":542.2,"prev_close":549.9},"JUBLFOOD":{"ltp":433.85,"pct":-0.99,"open":433.25,"high":438.75,"low":432.45,"prev_close":438.2},"CRISIL":{"ltp":4086.0,"pct":-0.19,"open":4142.55,"high":4142.55,"low":4083.0,"prev_close":4093.85},"KARURVYSYA":{"ltp":309.6,"pct":1.24,"open":305.0,"high":311.7,"low":300.95,"prev_close":305.8},"GODIGIT":{"ltp":307.3,"pct":-1.57,"open":312.0,"high":312.0,"low":307.3,"prev_close":312.2},"CUPID":{"ltp":209.1,"pct":-1.37,"open":213.95,"high":215.15,"low":205.05,"prev_close":212.0},"SYRMA":{"ltp":1440.25,"pct":-0.76,"open":1439.25,"high":1449.0,"low":1420.5,"prev_close":1451.25},"CHOLAHLDNG":{"ltp":1642.4,"pct":-0.66,"open":1658.8,"high":1661.0,"low":1623.35,"prev_close":1653.3},"SJVN":{"ltp":70.59,"pct":-0.42,"open":69.92,"high":70.96,"low":69.73,"prev_close":70.89},"ITI":{"ltp":290.15,"pct":-0.09,"open":290.7,"high":291.45,"low":288.0,"prev_close":290.4},"AMBER":{"ltp":7790.0,"pct":0.12,"open":7770.8,"high":7950.0,"low":7720.9,"prev_close":7780.8},"METROBRAND":{"ltp":1069.25,"pct":0.44,"open":1074.95,"high":1076.0,"low":1055.85,"prev_close":1064.55},"MRPL":{"ltp":165.7,"pct":2.0,"open":162.7,"high":170.0,"low":162.7,"prev_close":162.45},"LALPATHLAB":{"ltp":1731.9,"pct":2.31,"open":1677.3,"high":1737.9,"low":1671.9,"prev_close":1692.85},"MSUMI":{"ltp":40.23,"pct":0.15,"open":40.17,"high":40.3,"low":39.51,"prev_close":40.17},"STLTECH":{"ltp":517.1,"pct":-4.56,"open":535.0,"high":548.7,"low":516.55,"prev_close":541.8,"vwap":529.67,"vol":48000},"SHYAMMETL":{"ltp":1029.15,"pct":5.75,"open":975.0,"high":1039.7,"low":971.15,"prev_close":973.2,"vwap":1012.83,"vol":36000},"ACUTAAS":{"ltp":3469.0,"pct":2.21,"open":3363.05,"high":3470.95,"low":3363.05,"prev_close":3393.95},"SUMICHEM":{"ltp":531.4,"pct":3.46,"open":513.7,"high":533.5,"low":508.25,"prev_close":513.65,"vwap":523.24,"vol":77000},"ZFCVINDIA":{"ltp":2324.0,"pct":-0.43,"open":2333.8,"high":2355.0,"low":2317.0,"prev_close":2334.0},"RRKABEL":{"ltp":2304.7,"pct":3.58,"open":2195.55,"high":2312.0,"low":2172.1,"prev_close":2225.0,"vwap":2267.96,"vol":10000},"APOLLOTYRE":{"ltp":438.9,"pct":-0.3,"open":436.2,"high":441.85,"low":434.1,"prev_close":440.2},"NEULANDLAB":{"ltp":19245.45,"pct":-1.39,"open":19202.1,"high":19539.0,"low":18983.0,"prev_close":19516.65},"CEMPRO":{"ltp":1588.4,"pct":1.47,"open":1577.0,"high":1592.35,"low":1555.05,"prev_close":1565.45},"CGCL":{"ltp":258.35,"pct":2.52,"open":252.45,"high":260.0,"low":252.0,"prev_close":252.0,"vwap":255.72,"vol":115999},"NBCC":{"ltp":100.45,"pct":0.5,"open":99.2,"high":102.45,"low":97.95,"prev_close":99.95},"GUJENERGY":{"ltp":286.05,"pct":-1.16,"open":287.3,"high":289.0,"low":285.5,"prev_close":289.4},"CREDITACC":{"ltp":1520.75,"pct":-0.46,"open":1536.45,"high":1545.0,"low":1505.95,"prev_close":1527.8},"PTCIL":{"ltp":17650.0,"pct":0.22,"open":17405.45,"high":17713.95,"low":17405.4,"prev_close":17610.4},"DATAPATTNS":{"ltp":4277.95,"pct":-1.47,"open":4338.5,"high":4341.8,"low":4234.65,"prev_close":4341.85},"AWL":{"ltp":189.85,"pct":-0.05,"open":187.55,"high":191.5,"low":186.8,"prev_close":189.95},"ACMESOLAR":{"ltp":370.95,"pct":-1.57,"open":374.45,"high":374.45,"low":366.25,"prev_close":376.85},"RUBICON":{"ltp":1444.75,"pct":0.94,"open":1431.0,"high":1481.6,"low":1417.15,"prev_close":1431.35},"TENNIND":{"ltp":586.45,"pct":-0.47,"open":588.2,"high":592.15,"low":579.05,"prev_close":589.2},"TIMKEN":{"ltp":3173.3,"pct":-1.02,"open":3176.75,"high":3200.35,"low":3150.0,"prev_close":3206.1},"ACC":{"ltp":1374.1,"pct":-0.77,"open":1364.0,"high":1380.35,"low":1357.1,"prev_close":1384.75},"IIFL":{"ltp":554.5,"pct":0.35,"open":548.0,"high":560.75,"low":547.0,"prev_close":552.55},"SAILIFE":{"ltp":1274.1,"pct":0.79,"open":1271.55,"high":1287.7,"low":1255.45,"prev_close":1264.15},"GILLETTE":{"ltp":7903.0,"pct":0.74,"open":7844.1,"high":7955.0,"low":7813.95,"prev_close":7844.8},"FORCEMOT":{"ltp":17942.95,"pct":-1.15,"open":18098.35,"high":18105.9,"low":17810.0,"prev_close":18151.4},"ASAHIINDIA":{"ltp":921.3,"pct":0.68,"open":919.75,"high":928.75,"low":907.05,"prev_close":915.1},"CRAFTSMAN":{"ltp":9334.0,"pct":0.61,"open":9276.25,"high":9399.4,"low":9211.75,"prev_close":9276.95},"AADHARHFC":{"ltp":536.0,"pct":0.39,"open":533.55,"high":544.5,"low":525.05,"prev_close":533.9},"PPLPHARMA":{"ltp":173.85,"pct":-1.84,"open":176.5,"high":177.15,"low":173.05,"prev_close":177.1},"IRB":{"ltp":20.17,"pct":-0.69,"open":20.16,"high":20.4,"low":20.01,"prev_close":20.31},"KPIL":{"ltp":1329.05,"pct":-1.65,"open":1336.1,"high":1343.8,"low":1322.0,"prev_close":1351.3},"NETWEB":{"ltp":4217.0,"pct":-2.04,"open":4258.95,"high":4260.0,"low":4212.0,"prev_close":4304.65},"DEEPAKNTR":{"ltp":1651.9,"pct":0.57,"open":1630.0,"high":1663.0,"low":1614.0,"prev_close":1642.55},"REDINGTON":{"ltp":285.45,"pct":1.86,"open":277.6,"high":286.0,"low":275.2,"prev_close":280.25},"GRANULES":{"ltp":898.65,"pct":1.02,"open":890.05,"high":907.0,"low":885.95,"prev_close":889.55},"RBLBANK":{"ltp":380.2,"pct":-0.13,"open":377.1,"high":380.8,"low":374.75,"prev_close":380.7},"TATAELXSI":{"ltp":3768.2,"pct":2.08,"open":3690.0,"high":3777.0,"low":3670.95,"prev_close":3691.55},"RAMCOCEM":{"ltp":940.0,"pct":-0.07,"open":938.95,"high":945.05,"low":932.05,"prev_close":940.7},"IGL":{"ltp":152.8,"pct":-0.84,"open":153.45,"high":154.45,"low":152.45,"prev_close":154.1},"PFIZER":{"ltp":4747.2,"pct":0.39,"open":4728.55,"high":4754.95,"low":4709.3,"prev_close":4728.55},"EMMVEE":{"ltp":337.15,"pct":1.23,"open":333.05,"high":345.5,"low":332.0,"prev_close":333.05},"CESC":{"ltp":161.2,"pct":-1.71,"open":163.0,"high":164.75,"low":161.1,"prev_close":164.0},"KIOCL":{"ltp":376.8,"pct":-1.12,"open":375.05,"high":379.25,"low":375.05,"prev_close":381.05},"EIHOTEL":{"ltp":337.0,"pct":2.09,"open":327.1,"high":339.0,"low":326.75,"prev_close":330.1},"GRINDWELL":{"ltp":2038.0,"pct":-1.01,"open":2025.05,"high":2049.35,"low":2025.05,"prev_close":2058.85},"BELRISE":{"ltp":235.05,"pct":1.73,"open":231.1,"high":237.5,"low":229.05,"prev_close":231.05},"MTARTECH":{"ltp":6748.9,"pct":-5.0,"open":7001.5,"high":7001.5,"low":6748.9,"prev_close":7104.1,"vwap":6854.53,"vol":603200000},"AFFLE":{"ltp":1583.0,"pct":6.93,"open":1474.05,"high":1590.0,"low":1474.05,"prev_close":1480.45,"vwap":1560.27,"vol":83000},"GESHIP":{"ltp":1394.3,"pct":-1.95,"open":1402.05,"high":1440.0,"low":1387.85,"prev_close":1422.0},"CUB":{"ltp":224.7,"pct":-1.96,"open":228.65,"high":228.65,"low":224.1,"prev_close":229.2},"URBANCO":{"ltp":133.0,"pct":0.68,"open":132.15,"high":133.7,"low":131.15,"prev_close":132.1},"KAYNES":{"ltp":3304.2,"pct":-0.89,"open":3318.6,"high":3332.3,"low":3270.05,"prev_close":3333.9},"J&KBANK":{"ltp":184.45,"pct":-4.03,"open":188.8,"high":191.75,"low":183.5,"prev_close":192.2,"vwap":187.34,"vol":377000},"HBLENGINE":{"ltp":760.75,"pct":-0.66,"open":764.1,"high":765.9,"low":757.7,"prev_close":765.8},"ANANTRAJ":{"ltp":572.7,"pct":-2.29,"open":579.55,"high":587.0,"low":571.75,"prev_close":586.1},"PFOCUS":{"ltp":268.45,"pct":4.99,"open":267.9,"high":268.45,"low":267.9,"prev_close":255.7,"vwap":268.36,"vol":214000000},"SANSERA":{"ltp":3319.0,"pct":0.38,"open":3292.35,"high":3360.0,"low":3270.15,"prev_close":3306.45},"HATSUN":{"ltp":903.5,"pct":-0.12,"open":902.0,"high":906.95,"low":894.4,"prev_close":904.6},"KAJARIACER":{"ltp":1243.65,"pct":2.06,"open":1218.05,"high":1252.45,"low":1200.0,"prev_close":1218.6},"SAGILITY":{"ltp":42.05,"pct":-1.06,"open":42.18,"high":42.47,"low":41.83,"prev_close":42.5},"IFCI":{"ltp":76.2,"pct":-1.6,"open":76.3,"high":77.32,"low":75.96,"prev_close":77.44},"ERIS":{"ltp":1434.35,"pct":0.4,"open":1411.1,"high":1438.45,"low":1411.1,"prev_close":1428.7},"CAPLIPOINT":{"ltp":2609.3,"pct":0.92,"open":2583.7,"high":2637.95,"low":2563.15,"prev_close":2585.4},"ASTRAZEN":{"ltp":8143.65,"pct":0.24,"open":8113.55,"high":8198.0,"low":8022.7,"prev_close":8123.85},"SUNTV":{"ltp":496.55,"pct":-0.66,"open":495.8,"high":498.4,"low":494.0,"prev_close":499.85},"CARBORUNIV":{"ltp":1067.0,"pct":-2.78,"open":1086.65,"high":1093.55,"low":1062.8,"prev_close":1090.6,"vwap":1073.88,"vol":958700000},"SUNDRMFAST":{"ltp":961.55,"pct":2.3,"open":936.95,"high":963.0,"low":936.95,"prev_close":939.9},"ONESOURCE":{"ltp":1671.5,"pct":3.49,"open":1617.75,"high":1686.9,"low":1610.8,"prev_close":1615.1,"vwap":1650.47,"vol":12000},"SAMMAANCAP":{"ltp":163.6,"pct":-1.68,"open":165.0,"high":166.25,"low":163.4,"prev_close":166.4},"THANGAMAYL":{"ltp":6441.25,"pct":-1.49,"open":6548.35,"high":6548.35,"low":6385.55,"prev_close":6538.7},"DEEPAKFERT":{"ltp":1482.25,"pct":-2.89,"open":1485.35,"high":1523.5,"low":1478.05,"prev_close":1526.3,"vwap":1499.73,"vol":15000},"RATNAMANI":{"ltp":2675.45,"pct":-0.75,"open":2675.05,"high":2714.95,"low":2675.0,"prev_close":2695.7},"ZYDUSWELL":{"ltp":587.15,"pct":-0.85,"open":591.8,"high":593.95,"low":583.35,"prev_close":592.2},"OLAELEC":{"ltp":40.19,"pct":-0.57,"open":40.1,"high":40.75,"low":39.58,"prev_close":40.42},"CHALET":{"ltp":848.8,"pct":1.12,"open":838.6,"high":853.95,"low":827.15,"prev_close":839.4},"CAMS":{"ltp":786.15,"pct":-0.44,"open":789.15,"high":790.0,"low":776.85,"prev_close":789.6},"VTL":{"ltp":642.0,"pct":0.85,"open":628.75,"high":643.25,"low":628.75,"prev_close":636.6},"TRITURBINE":{"ltp":617.95,"pct":1.98,"open":603.7,"high":625.0,"low":596.4,"prev_close":605.95},"AETHER":{"ltp":1457.9,"pct":-2.53,"open":1477.15,"high":1483.9,"low":1454.75,"prev_close":1495.7,"vwap":1467.71,"vol":706300000},"CMPDI":{"ltp":264.15,"pct":-1.09,"open":265.35,"high":269.8,"low":263.0,"prev_close":267.05},"BRIGADE":{"ltp":567.2,"pct":-1.3,"open":569.25,"high":575.95,"low":565.0,"prev_close":574.65},"BAYERCROP":{"ltp":4106.2,"pct":-0.62,"open":4115.05,"high":4122.9,"low":4099.05,"prev_close":4131.75},"FSL":{"ltp":262.45,"pct":1.04,"open":256.35,"high":263.45,"low":253.5,"prev_close":259.75},"JSWCEMENT":{"ltp":138.1,"pct":-0.04,"open":138.1,"high":139.6,"low":136.95,"prev_close":138.15},"CHAMBLFERT":{"ltp":454.0,"pct":0.1,"open":451.95,"high":456.0,"low":448.0,"prev_close":453.55},"TDPOWERSYS":{"ltp":1155.0,"pct":0.43,"open":1140.0,"high":1184.75,"low":1119.85,"prev_close":1150.1},"CHOICEIN":{"ltp":822.55,"pct":-1.54,"open":832.85,"high":832.9,"low":821.0,"prev_close":835.4},"SHRIPISTON":{"ltp":4231.7,"pct":1.02,"open":4179.95,"high":4239.9,"low":4128.1,"prev_close":4189.05},"JYOTICNC":{"ltp":786.8,"pct":-1.21,"open":809.9,"high":809.9,"low":785.7,"prev_close":796.4},"EMAMILTD":{"ltp":424.05,"pct":0.65,"open":420.05,"high":425.0,"low":417.35,"prev_close":421.3},"ABDL":{"ltp":639.05,"pct":-1.46,"open":648.1,"high":648.1,"low":635.0,"prev_close":648.55},"PINELABS":{"ltp":153.6,"pct":5.68,"open":145.25,"high":156.6,"low":145.25,"prev_close":145.35,"vwap":152.77,"vol":2097000},"PSB":{"ltp":25.0,"pct":0.08,"open":24.93,"high":25.24,"low":24.7,"prev_close":24.98},"ATUL":{"ltp":6300.0,"pct":1.01,"open":6216.75,"high":6357.1,"low":6183.5,"prev_close":6237.25},"GMDCLTD":{"ltp":588.65,"pct":-0.2,"open":582.7,"high":595.9,"low":581.0,"prev_close":589.85},"LMW":{"ltp":16303.0,"pct":0.87,"open":16000.0,"high":16420.0,"low":15961.4,"prev_close":16162.4},"ELGIEQUIP":{"ltp":575.05,"pct":-0.21,"open":574.2,"high":580.0,"low":569.5,"prev_close":576.25},"CASTROLIND":{"ltp":184.05,"pct":0.16,"open":183.75,"high":184.75,"low":183.4,"prev_close":183.75},"TATACHEM":{"ltp":713.9,"pct":-0.85,"open":714.85,"high":719.15,"low":711.3,"prev_close":720.0},"NATCOPHARM":{"ltp":977.8,"pct":-0.58,"open":985.05,"high":988.15,"low":963.0,"prev_close":983.55},"TRAVELFOOD":{"ltp":1329.0,"pct":1.66,"open":1345.0,"high":1345.0,"low":1311.8,"prev_close":1307.25},"CIEINDIA":{"ltp":470.7,"pct":1.35,"open":458.6,"high":472.55,"low":458.55,"prev_close":464.45},"AARTIIND":{"ltp":479.5,"pct":-0.96,"open":481.55,"high":488.15,"low":476.5,"prev_close":484.15},"JINDALSAW":{"ltp":272.1,"pct":-1.38,"open":271.1,"high":273.95,"low":268.9,"prev_close":275.9},"GABRIEL":{"ltp":1243.25,"pct":-0.62,"open":1236.3,"high":1272.5,"low":1227.85,"prev_close":1251.0},"GPIL":{"ltp":252.9,"pct":-0.61,"open":251.05,"high":254.5,"low":249.45,"prev_close":254.45},"CENTURYPLY":{"ltp":788.0,"pct":-0.24,"open":786.65,"high":792.95,"low":784.25,"prev_close":789.9},"INOXINDIA":{"ltp":1934.0,"pct":-2.22,"open":1983.2,"high":1988.2,"low":1934.0,"prev_close":1977.95},"GALLANTT":{"ltp":701.55,"pct":5.0,"open":665.0,"high":701.55,"low":665.0,"prev_close":668.15,"vwap":699.76,"vol":35000},"CHENNPETRO":{"ltp":1177.15,"pct":-0.41,"open":1181.8,"high":1233.7,"low":1176.05,"prev_close":1181.8},"CROMPTON":{"ltp":262.5,"pct":0.32,"open":262.0,"high":263.05,"low":259.4,"prev_close":261.65},"BHARATCOAL":{"ltp":37.46,"pct":-0.29,"open":37.2,"high":37.72,"low":36.92,"prev_close":37.57},"COHANCE":{"ltp":451.25,"pct":-0.07,"open":454.35,"high":454.35,"low":447.05,"prev_close":451.55},"SARDAEN":{"ltp":494.8,"pct":-1.37,"open":502.9,"high":502.9,"low":493.55,"prev_close":501.65},"POLYMED":{"ltp":1648.65,"pct":-1.03,"open":1652.95,"high":1664.95,"low":1641.6,"prev_close":1665.85},"MINDACORP":{"ltp":698.45,"pct":-0.04,"open":701.25,"high":701.35,"low":686.85,"prev_close":698.75},"ZENTEC":{"ltp":1833.4,"pct":-2.48,"open":1877.6,"high":1877.6,"low":1827.9,"prev_close":1880.1,"vwap":1842.73,"vol":12000},"PGEL":{"ltp":593.0,"pct":1.69,"open":574.3,"high":607.8,"low":572.6,"prev_close":583.15},"NAVA":{"ltp":601.75,"pct":0.42,"open":598.55,"high":603.0,"low":593.15,"prev_close":599.25},"ARE&M":{"ltp":901.9,"pct":1.6,"open":886.95,"high":905.05,"low":873.65,"prev_close":887.7},"KSB":{"ltp":950.4,"pct":0.95,"open":941.0,"high":956.45,"low":930.25,"prev_close":941.45},"NSDL":{"ltp":845.3,"pct":-0.63,"open":847.0,"high":855.0,"low":842.0,"prev_close":850.65},"SYNGENE":{"ltp":417.2,"pct":-0.75,"open":417.8,"high":421.9,"low":416.0,"prev_close":420.35},"AEQUS":{"ltp":244.95,"pct":-1.59,"open":248.8,"high":251.4,"low":243.65,"prev_close":248.9},"THELEELA":{"ltp":501.8,"pct":0.11,"open":493.65,"high":508.75,"low":493.65,"prev_close":501.25},"BIKAJI":{"ltp":646.0,"pct":0.46,"open":638.0,"high":648.65,"low":637.9,"prev_close":643.05},"GRWRHITECH":{"ltp":7007.45,"pct":0.51,"open":7018.45,"high":7173.0,"low":6945.0,"prev_close":6971.95},"DCMSHRIRAM":{"ltp":1041.0,"pct":-1.07,"open":1052.95,"high":1052.95,"low":1018.0,"prev_close":1052.3},"WELSPUNLIV":{"ltp":171.0,"pct":2.92,"open":165.2,"high":172.8,"low":163.5,"prev_close":166.15,"vwap":169.88,"vol":135000},"BBOX":{"ltp":901.0,"pct":-2.26,"open":917.0,"high":917.0,"low":901.0,"prev_close":921.85},"ASTRAMICRO":{"ltp":1748.3,"pct":-3.08,"open":1809.0,"high":1809.0,"low":1734.8,"prev_close":1803.8,"vwap":1753.65,"vol":22000},"NIVABUPA":{"ltp":89.02,"pct":2.9,"open":86.5,"high":89.44,"low":86.01,"prev_close":86.51,"vwap":88.3,"vol":231000},"TBOTEK":{"ltp":1521.0,"pct":1.11,"open":1501.05,"high":1528.0,"low":1490.65,"prev_close":1504.35},"FINCABLES":{"ltp":1054.95,"pct":0.02,"open":1057.3,"high":1076.0,"low":1039.05,"prev_close":1054.75},"CCL":{"ltp":1230.95,"pct":1.56,"open":1198.7,"high":1241.85,"low":1190.5,"prev_close":1212.0},"AGARWALEYE":{"ltp":499.9,"pct":3.41,"open":470.45,"high":502.0,"low":470.45,"prev_close":483.4,"vwap":492.82,"vol":938900000},"APLLTD":{"ltp":833.05,"pct":-0.52,"open":844.95,"high":844.95,"low":826.45,"prev_close":837.4},"KPITTECH":{"ltp":570.25,"pct":1.5,"open":559.4,"high":572.3,"low":557.05,"prev_close":561.8},"KANSAINER":{"ltp":201.55,"pct":-0.49,"open":202.55,"high":202.55,"low":200.35,"prev_close":202.55},"CLEANMAX":{"ltp":1326.2,"pct":-0.42,"open":1316.45,"high":1360.0,"low":1312.2,"prev_close":1331.75},"SOBHA":{"ltp":1511.65,"pct":0.11,"open":1521.5,"high":1551.2,"low":1486.6,"prev_close":1510.05},"VEDPOWER":{"ltp":41.25,"pct":-1.58,"open":41.51,"high":42.48,"low":41.07,"prev_close":41.86},"AZAD":{"ltp":2409.35,"pct":-2.8,"open":2449.9,"high":2530.0,"low":2402.2,"prev_close":2478.65,"vwap":2461.71,"vol":47000},"JBMA":{"ltp":680.7,"pct":-0.58,"open":679.05,"high":685.25,"low":673.2,"prev_close":684.7},"KIRLOSBROS":{"ltp":1950.1,"pct":1.63,"open":1927.6,"high":1965.0,"low":1905.25,"prev_close":1918.8},"FINEORG":{"ltp":5058.45,"pct":1.17,"open":5009.0,"high":5067.5,"low":4928.0,"prev_close":4999.75},"FIVESTAR":{"ltp":542.7,"pct":-0.56,"open":549.7,"high":549.7,"low":538.55,"prev_close":545.75},"ECLERX":{"ltp":1642.05,"pct":1.22,"open":1612.4,"high":1660.0,"low":1603.65,"prev_close":1622.3},"JUBLPHARMA":{"ltp":965.8,"pct":0.51,"open":961.0,"high":973.0,"low":961.0,"prev_close":960.9},"MAHSCOOTER":{"ltp":13370.0,"pct":1.85,"open":13020.1,"high":13370.0,"low":13020.05,"prev_close":13127.7},"ABREL":{"ltp":1418.4,"pct":-1.74,"open":1428.9,"high":1442.05,"low":1411.35,"prev_close":1443.55},"RAINBOW":{"ltp":1494.2,"pct":1.49,"open":1464.6,"high":1497.1,"low":1443.95,"prev_close":1472.2},"VOGL":{"ltp":38.87,"pct":0.34,"open":38.94,"high":39.9,"low":38.58,"prev_close":38.74},"KFINTECH":{"ltp":911.6,"pct":1.12,"open":895.5,"high":913.4,"low":891.05,"prev_close":901.5},"CEATLTD":{"ltp":3864.7,"pct":0.05,"open":3815.25,"high":3906.0,"low":3794.85,"prev_close":3862.7},"FRACTAL":{"ltp":863.4,"pct":1.87,"open":844.95,"high":865.95,"low":838.0,"prev_close":847.55},"APTUS":{"ltp":292.45,"pct":3.07,"open":283.75,"high":298.8,"low":280.45,"prev_close":283.75,"vwap":292.79,"vol":48000},"ANURAS":{"ltp":1279.7,"pct":0.96,"open":1299.6,"high":1299.6,"low":1265.0,"prev_close":1267.55},"USHAMART":{"ltp":510.0,"pct":0.04,"open":510.0,"high":514.35,"low":505.7,"prev_close":509.8},"VIJAYA":{"ltp":1405.0,"pct":1.12,"open":1379.05,"high":1405.5,"low":1360.0,"prev_close":1389.45},"BEML":{"ltp":1846.4,"pct":-0.8,"open":1860.2,"high":1860.2,"low":1836.0,"prev_close":1861.35},"CANHLIFE":{"ltp":150.9,"pct":4.47,"open":145.0,"high":158.7,"low":145.0,"prev_close":144.45,"vwap":153.97,"vol":809000},"BASF":{"ltp":3529.6,"pct":-0.45,"open":3522.9,"high":3534.9,"low":3494.3,"prev_close":3545.4},"IGIL":{"ltp":343.0,"pct":-1.12,"open":346.9,"high":346.9,"low":339.85,"prev_close":346.9},"PRIVISCL":{"ltp":3613.6,"pct":-1.34,"open":3634.75,"high":3652.9,"low":3612.45,"prev_close":3662.6},"VISL":{"ltp":36.41,"pct":4.99,"open":35.4,"high":36.41,"low":35.22,"prev_close":34.68,"vwap":36.13,"vol":13901000},"HAPPYFORGE":{"ltp":1567.75,"pct":-0.82,"open":1598.9,"high":1598.9,"low":1564.6,"prev_close":1580.65},"PARADEEP":{"ltp":142.4,"pct":0.39,"open":140.2,"high":143.15,"low":138.9,"prev_close":141.85},"VENTIVE":{"ltp":623.35,"pct":-0.14,"open":620.0,"high":624.0,"low":618.6,"prev_close":624.2},"ARVIND":{"ltp":537.7,"pct":2.2,"open":525.1,"high":539.15,"low":516.0,"prev_close":526.1},"INOXWIND":{"ltp":80.83,"pct":-1.94,"open":82.1,"high":82.24,"low":80.75,"prev_close":82.43},"HONASA":{"ltp":473.05,"pct":0.36,"open":471.2,"high":478.0,"low":465.4,"prev_close":471.35},"APOLLO":{"ltp":401.95,"pct":-1.69,"open":408.45,"high":408.45,"low":400.35,"prev_close":408.85},"INGERRAND":{"ltp":4440.0,"pct":-0.35,"open":4440.75,"high":4479.95,"low":4292.1,"prev_close":4455.5},"WABAG":{"ltp":2218.95,"pct":-0.08,"open":2214.95,"high":2252.4,"low":2179.1,"prev_close":2220.7},"DOMS":{"ltp":2373.5,"pct":-0.08,"open":2366.4,"high":2383.45,"low":2335.0,"prev_close":2375.5},"CONCORDBIO":{"ltp":1312.7,"pct":0.66,"open":1309.1,"high":1320.0,"low":1269.05,"prev_close":1304.1},"SPLPETRO":{"ltp":728.25,"pct":-0.82,"open":730.0,"high":734.45,"low":727.3,"prev_close":734.25},"EIDPARRY":{"ltp":767.6,"pct":1.25,"open":756.1,"high":774.8,"low":745.5,"prev_close":758.15},"SHADOWFAX":{"ltp":229.75,"pct":0.79,"open":227.55,"high":233.05,"low":222.9,"prev_close":227.95},"CARTRADE":{"ltp":2795.6,"pct":-0.48,"open":2873.55,"high":2873.55,"low":2788.35,"prev_close":2808.95},"ALIVUS":{"ltp":1164.0,"pct":0.31,"open":1160.15,"high":1175.0,"low":1144.85,"prev_close":1160.45},"JSWDULUX":{"ltp":2949.15,"pct":0.79,"open":2957.95,"high":2957.95,"low":2906.45,"prev_close":2926.15},"VGUARD":{"ltp":304.45,"pct":-0.29,"open":306.2,"high":306.2,"low":302.95,"prev_close":305.35},"SKFINDUS":{"ltp":2840.35,"pct":0.12,"open":2807.45,"high":2860.0,"low":2807.45,"prev_close":2836.95},"SCI":{"ltp":284.6,"pct":-0.11,"open":280.3,"high":287.0,"low":280.0,"prev_close":284.9},"DEVYANI":{"ltp":113.2,"pct":0.8,"open":111.15,"high":114.75,"low":111.05,"prev_close":112.3},"VINATIORGA":{"ltp":1329.1,"pct":-0.39,"open":1321.9,"high":1333.1,"low":1313.0,"prev_close":1334.35},"KEC":{"ltp":495.55,"pct":-1.86,"open":500.0,"high":500.0,"low":494.25,"prev_close":504.95},"LLOYDSENGG":{"ltp":93.07,"pct":2.74,"open":89.2,"high":95.01,"low":89.2,"prev_close":90.59,"vwap":93.17,"vol":1712000},"HOMEFIRST":{"ltp":1257.0,"pct":2.8,"open":1222.05,"high":1283.4,"low":1210.05,"prev_close":1222.8,"vwap":1265.58,"vol":23000},"GRAVITA":{"ltp":1839.4,"pct":-0.79,"open":1859.75,"high":1869.6,"low":1839.4,"prev_close":1854.0},"PARKHOSPS":{"ltp":294.8,"pct":3.11,"open":287.95,"high":295.45,"low":283.8,"prev_close":285.9,"vwap":292.33,"vol":84000},"LTFOODS":{"ltp":385.9,"pct":-0.84,"open":387.9,"high":388.3,"low":383.15,"prev_close":389.15},"PCBL":{"ltp":322.3,"pct":4.09,"open":306.55,"high":327.5,"low":304.45,"prev_close":309.65,"vwap":319.85,"vol":163000},"TRIDENT":{"ltp":25.65,"pct":0.55,"open":25.23,"high":25.8,"low":25.1,"prev_close":25.51},"504340":{"ltp":7.14,"pct":-2.99,"open":7.69,"high":7.69,"low":7.14,"prev_close":7.36,"vwap":7.23,"vol":24000},"ENGINERSIN":{"ltp":235.9,"pct":-1.52,"open":239.6,"high":240.0,"low":235.3,"prev_close":239.55},"UTIAMC":{"ltp":1031.05,"pct":2.7,"open":1011.05,"high":1034.2,"low":1004.5,"prev_close":1003.9,"vwap":1022.32,"vol":38000},"507960":{"ltp":190.25,"pct":0.96,"open":188.5,"high":191.0,"low":185.0,"prev_close":188.45},"514060":{"ltp":4.71,"pct":1.51,"open":4.73,"high":4.95,"low":4.71,"prev_close":4.64},"ATLANTAELE":{"ltp":1719.8,"pct":1.42,"open":1663.45,"high":1719.85,"low":1663.45,"prev_close":1695.7},"530881":{"ltp":5.8,"pct":-2.68,"open":5.9,"high":5.96,"low":5.66,"prev_close":5.96,"vwap":5.8,"vol":187000},"539983":{"ltp":12.5,"pct":0.0,"open":12.5,"high":12.5,"low":12.5,"prev_close":10.0},"EIMCOELECO":{"ltp":1787.85,"pct":2.52,"open":1785.95,"high":1808.05,"low":1764.05,"prev_close":1743.9,"vwap":1792.56,"vol":150300000},"CORONA":{"ltp":2071.95,"pct":1.74,"open":2054.95,"high":2096.85,"low":2050.75,"prev_close":2036.6},"UJJIVANSFB":{"ltp":65.0,"pct":-0.41,"open":65.0,"high":65.82,"low":64.01,"prev_close":65.27},"GMBREW":{"ltp":929.8,"pct":-1.18,"open":923.6,"high":940.9,"low":920.7,"prev_close":940.9},"SHARDUL":{"ltp":40.46,"pct":19.99,"open":40.46,"high":40.46,"low":40.46,"prev_close":33.72,"vwap":40.46,"vol":16000},"512361":{"ltp":33.15,"pct":-0.3,"open":33.0,"high":33.15,"low":31.71,"prev_close":33.25},"512301":{"ltp":33.81,"pct":5.0,"open":33.81,"high":33.81,"low":33.81,"prev_close":32.2,"vwap":33.81,"vol":461300000},"AVANTIFEED":{"ltp":925.85,"pct":0.23,"open":916.4,"high":938.05,"low":909.6,"prev_close":923.7},"523465":{"ltp":52.49,"pct":-1.67,"open":52.95,"high":52.95,"low":52.49,"prev_close":53.38},"UMIYA-MRO":{"ltp":90.0,"pct":-1.51,"open":85.11,"high":90.19,"low":85.11,"prev_close":91.38},"526071":{"ltp":603.0,"pct":1.46,"open":580.0,"high":604.85,"low":575.0,"prev_close":594.35},"538547":{"ltp":0.92,"pct":-1.08,"open":0.92,"high":0.92,"low":0.92,"prev_close":0.93},"ELECON":{"ltp":511.2,"pct":0.18,"open":493.25,"high":520.5,"low":493.25,"prev_close":510.3},"INDBANK":{"ltp":33.32,"pct":-2.23,"open":35.0,"high":35.0,"low":33.32,"prev_close":34.08}}}